[{"title":"b'1-Methylhistidine'Doc_129544","h_idx":22,"t_idx":1,"r":"P17"},{"title":"b'1-Methylhistidine'Doc_129545","h_idx":22,"t_idx":10,"r":"P17"},{"title":"b'1-Methylhistidine'Doc_129569","h_idx":19,"t_idx":4,"r":"P17"},{"title":"b'1-Methylhistidine'Doc_129569","h_idx":19,"t_idx":22,"r":"P17"},{"title":"b'1-Methylhistidine'Doc_129602","h_idx":8,"t_idx":3,"r":"P17"},{"title":"b'1-Methylhistidine'Doc_129629","h_idx":24,"t_idx":14,"r":"P17"},{"title":"b'1-Methylhistidine'Doc_129631","h_idx":4,"t_idx":16,"r":"P17"},{"title":"b'(2S)-2-amino-3-(1-methyl-1H-imidazol-4-yl)propanoic acid'Doc_129637","h_idx":22,"t_idx":1,"r":"P17"},{"title":"b'(2S)-2-amino-3-(1-methyl-1H-imidazol-4-yl)propanoic acid'Doc_129638","h_idx":22,"t_idx":10,"r":"P17"},{"title":"b'(2S)-2-amino-3-(1-methyl-1H-imidazol-4-yl)propanoic acid'Doc_129662","h_idx":19,"t_idx":4,"r":"P17"},{"title":"b'(2S)-2-amino-3-(1-methyl-1H-imidazol-4-yl)propanoic acid'Doc_129662","h_idx":19,"t_idx":22,"r":"P17"},{"title":"b'(2S)-2-amino-3-(1-methyl-1H-imidazol-4-yl)propanoic acid'Doc_129695","h_idx":8,"t_idx":3,"r":"P17"},{"title":"b'(2S)-2-amino-3-(1-methyl-1H-imidazol-4-yl)propanoic acid'Doc_129722","h_idx":24,"t_idx":14,"r":"P17"},{"title":"b'(2S)-2-amino-3-(1-methyl-1H-imidazol-4-yl)propanoic acid'Doc_129724","h_idx":4,"t_idx":16,"r":"P17"},{"title":"b'1,3-Diaminopropane'Doc_129730","h_idx":22,"t_idx":1,"r":"P17"},{"title":"b'1,3-Diaminopropane'Doc_129731","h_idx":22,"t_idx":10,"r":"P17"},{"title":"b'1,3-Diaminopropane'Doc_129755","h_idx":19,"t_idx":4,"r":"P17"},{"title":"b'1,3-Diaminopropane'Doc_129755","h_idx":19,"t_idx":22,"r":"P17"},{"title":"b'1,3-Diaminopropane'Doc_129788","h_idx":8,"t_idx":3,"r":"P17"},{"title":"b'1,3-Diaminopropane'Doc_129815","h_idx":24,"t_idx":14,"r":"P17"},{"title":"b'1,3-Diaminopropane'Doc_129817","h_idx":4,"t_idx":16,"r":"P17"},{"title":"b'propane-1,3-diamine'Doc_129892","h_idx":13,"t_idx":1,"r":"P17"},{"title":"b'propane-1,3-diamine'Doc_129901","h_idx":7,"t_idx":19,"r":"P17"},{"title":"b'2-Ketobutyric acid'Doc_129927","h_idx":9,"t_idx":4,"r":"P17"},{"title":"b'2-Ketobutyric acid'Doc_129928","h_idx":5,"t_idx":6,"r":"P17"},{"title":"b'2-Ketobutyric acid'Doc_129928","h_idx":8,"t_idx":6,"r":"P17"},{"title":"b'2-Ketobutyric acid'Doc_129984","h_idx":2,"t_idx":1,"r":"P17"},{"title":"b'2-Ketobutyric acid'Doc_129984","h_idx":14,"t_idx":2,"r":"P17"},{"title":"b'2-Ketobutyric acid'Doc_129992","h_idx":2,"t_idx":8,"r":"P17"},{"title":"b'2-Ketobutyric acid'Doc_129992","h_idx":8,"t_idx":2,"r":"P17"},{"title":"b'2-oxobutanoic acid'Doc_130044","h_idx":2,"t_idx":8,"r":"P17"},{"title":"b'2-oxobutanoic acid'Doc_130044","h_idx":8,"t_idx":2,"r":"P17"},{"title":"b'2-oxobutanoic acid'Doc_130065","h_idx":2,"t_idx":1,"r":"P17"},{"title":"b'2-oxobutanoic acid'Doc_130065","h_idx":14,"t_idx":2,"r":"P17"},{"title":"b'2-oxobutanoic acid'Doc_130071","h_idx":5,"t_idx":6,"r":"P17"},{"title":"b'2-oxobutanoic acid'Doc_130071","h_idx":8,"t_idx":6,"r":"P17"},{"title":"b'2-oxobutanoic acid'Doc_130081","h_idx":9,"t_idx":4,"r":"P17"},{"title":"b'2-Hydroxybutyric acid'Doc_130094","h_idx":2,"t_idx":1,"r":"P17"},{"title":"b'2-Hydroxybutyric acid'Doc_130094","h_idx":14,"t_idx":2,"r":"P17"},{"title":"b'2-Hydroxybutyric acid'Doc_130107","h_idx":2,"t_idx":8,"r":"P17"},{"title":"b'2-Hydroxybutyric acid'Doc_130107","h_idx":8,"t_idx":2,"r":"P17"},{"title":"b'2-Hydroxybutyric acid'Doc_130127","h_idx":5,"t_idx":6,"r":"P17"},{"title":"b'2-Hydroxybutyric acid'Doc_130127","h_idx":8,"t_idx":6,"r":"P17"},{"title":"b'2-Hydroxybutyric acid'Doc_130149","h_idx":9,"t_idx":4,"r":"P17"},{"title":"b'(2S)-2-hydroxybutanoic acid'Doc_130182","h_idx":2,"t_idx":1,"r":"P17"},{"title":"b'(2S)-2-hydroxybutanoic acid'Doc_130182","h_idx":14,"t_idx":2,"r":"P17"},{"title":"b'(2S)-2-hydroxybutanoic acid'Doc_130195","h_idx":2,"t_idx":8,"r":"P17"},{"title":"b'(2S)-2-hydroxybutanoic acid'Doc_130195","h_idx":8,"t_idx":2,"r":"P17"},{"title":"b'(2S)-2-hydroxybutanoic acid'Doc_130215","h_idx":5,"t_idx":6,"r":"P17"},{"title":"b'(2S)-2-hydroxybutanoic acid'Doc_130215","h_idx":8,"t_idx":6,"r":"P17"},{"title":"b'(2S)-2-hydroxybutanoic acid'Doc_130237","h_idx":9,"t_idx":4,"r":"P17"},{"title":"b'2-Methoxyestrone'Doc_130270","h_idx":2,"t_idx":1,"r":"P17"},{"title":"b'2-Methoxyestrone'Doc_130270","h_idx":14,"t_idx":2,"r":"P17"},{"title":"b'2-Methoxyestrone'Doc_130283","h_idx":2,"t_idx":8,"r":"P17"},{"title":"b'2-Methoxyestrone'Doc_130283","h_idx":8,"t_idx":2,"r":"P17"},{"title":"b'2-Methoxyestrone'Doc_130303","h_idx":5,"t_idx":6,"r":"P17"},{"title":"b'2-Methoxyestrone'Doc_130303","h_idx":8,"t_idx":6,"r":"P17"},{"title":"b'2-Methoxyestrone'Doc_130325","h_idx":9,"t_idx":4,"r":"P17"},{"title":"b'(1S,10R,11S,15S)-5-hydroxy-4-methoxy-15-methyltetracyclo[8.7.0.0^{2,7}.0^{11,15}]heptadeca-2(7),3,5-trien-14-one'Doc_130358","h_idx":2,"t_idx":1,"r":"P17"},{"title":"b'(1S,10R,11S,15S)-5-hydroxy-4-methoxy-15-methyltetracyclo[8.7.0.0^{2,7}.0^{11,15}]heptadeca-2(7),3,5-trien-14-one'Doc_130358","h_idx":14,"t_idx":2,"r":"P17"},{"title":"b'(1S,10R,11S,15S)-5-hydroxy-4-methoxy-15-methyltetracyclo[8.7.0.0^{2,7}.0^{11,15}]heptadeca-2(7),3,5-trien-14-one'Doc_130371","h_idx":2,"t_idx":8,"r":"P17"},{"title":"b'(1S,10R,11S,15S)-5-hydroxy-4-methoxy-15-methyltetracyclo[8.7.0.0^{2,7}.0^{11,15}]heptadeca-2(7),3,5-trien-14-one'Doc_130371","h_idx":8,"t_idx":2,"r":"P17"},{"title":"b'(1S,10R,11S,15S)-5-hydroxy-4-methoxy-15-methyltetracyclo[8.7.0.0^{2,7}.0^{11,15}]heptadeca-2(7),3,5-trien-14-one'Doc_130391","h_idx":5,"t_idx":6,"r":"P17"},{"title":"b'(1S,10R,11S,15S)-5-hydroxy-4-methoxy-15-methyltetracyclo[8.7.0.0^{2,7}.0^{11,15}]heptadeca-2(7),3,5-trien-14-one'Doc_130391","h_idx":8,"t_idx":6,"r":"P17"},{"title":"b'(1S,10R,11S,15S)-5-hydroxy-4-methoxy-15-methyltetracyclo[8.7.0.0^{2,7}.0^{11,15}]heptadeca-2(7),3,5-trien-14-one'Doc_130413","h_idx":9,"t_idx":4,"r":"P17"},{"title":"b'3-Hydroxybutyric acid'Doc_130435","h_idx":2,"t_idx":1,"r":"P17"},{"title":"b'3-Hydroxybutyric acid'Doc_130435","h_idx":14,"t_idx":2,"r":"P17"},{"title":"b'3-Hydroxybutyric acid'Doc_130506","h_idx":2,"t_idx":8,"r":"P17"},{"title":"b'3-Hydroxybutyric acid'Doc_130506","h_idx":8,"t_idx":2,"r":"P17"},{"title":"b'3-Hydroxybutyric acid'Doc_130508","h_idx":5,"t_idx":6,"r":"P17"},{"title":"b'3-Hydroxybutyric acid'Doc_130508","h_idx":8,"t_idx":6,"r":"P17"},{"title":"b'(3R)-3-hydroxybutanoic acid'Doc_130525","h_idx":2,"t_idx":1,"r":"P17"},{"title":"b'(3R)-3-hydroxybutanoic acid'Doc_130525","h_idx":14,"t_idx":2,"r":"P17"},{"title":"b'(3R)-3-hydroxybutanoic acid'Doc_130596","h_idx":2,"t_idx":8,"r":"P17"},{"title":"b'(3R)-3-hydroxybutanoic acid'Doc_130596","h_idx":8,"t_idx":2,"r":"P17"},{"title":"b'(3R)-3-hydroxybutanoic acid'Doc_130598","h_idx":5,"t_idx":6,"r":"P17"},{"title":"b'(3R)-3-hydroxybutanoic acid'Doc_130598","h_idx":8,"t_idx":6,"r":"P17"},{"title":"b'Deoxyuridine'Doc_130615","h_idx":2,"t_idx":1,"r":"P17"},{"title":"b'Deoxyuridine'Doc_130615","h_idx":14,"t_idx":2,"r":"P17"},{"title":"b'Deoxyuridine'Doc_130686","h_idx":2,"t_idx":8,"r":"P17"},{"title":"b'Deoxyuridine'Doc_130686","h_idx":8,"t_idx":2,"r":"P17"},{"title":"b'Deoxyuridine'Doc_130688","h_idx":5,"t_idx":6,"r":"P17"},{"title":"b'Deoxyuridine'Doc_130688","h_idx":8,"t_idx":6,"r":"P17"},{"title":"b'1-[(2R,4S,5R)-4-hydroxy-5-(hydroxymethyl)oxolan-2-yl]-1,2,3,4-tetrahydropyrimidine-2,4-dione'Doc_130705","h_idx":2,"t_idx":1,"r":"P17"},{"title":"b'1-[(2R,4S,5R)-4-hydroxy-5-(hydroxymethyl)oxolan-2-yl]-1,2,3,4-tetrahydropyrimidine-2,4-dione'Doc_130705","h_idx":14,"t_idx":2,"r":"P17"},{"title":"b'1-[(2R,4S,5R)-4-hydroxy-5-(hydroxymethyl)oxolan-2-yl]-1,2,3,4-tetrahydropyrimidine-2,4-dione'Doc_130776","h_idx":2,"t_idx":8,"r":"P17"},{"title":"b'1-[(2R,4S,5R)-4-hydroxy-5-(hydroxymethyl)oxolan-2-yl]-1,2,3,4-tetrahydropyrimidine-2,4-dione'Doc_130776","h_idx":8,"t_idx":2,"r":"P17"},{"title":"b'1-[(2R,4S,5R)-4-hydroxy-5-(hydroxymethyl)oxolan-2-yl]-1,2,3,4-tetrahydropyrimidine-2,4-dione'Doc_130778","h_idx":5,"t_idx":6,"r":"P17"},{"title":"b'1-[(2R,4S,5R)-4-hydroxy-5-(hydroxymethyl)oxolan-2-yl]-1,2,3,4-tetrahydropyrimidine-2,4-dione'Doc_130778","h_idx":8,"t_idx":6,"r":"P17"},{"title":"b'Deoxycytidine'Doc_130795","h_idx":2,"t_idx":1,"r":"P17"},{"title":"b'Deoxycytidine'Doc_130795","h_idx":14,"t_idx":2,"r":"P17"},{"title":"b'Deoxycytidine'Doc_130866","h_idx":2,"t_idx":8,"r":"P17"},{"title":"b'Deoxycytidine'Doc_130866","h_idx":8,"t_idx":2,"r":"P17"},{"title":"b'Deoxycytidine'Doc_130868","h_idx":5,"t_idx":6,"r":"P17"},{"title":"b'Deoxycytidine'Doc_130868","h_idx":8,"t_idx":6,"r":"P17"},{"title":"b'4-amino-1-[(2R,4S,5R)-4-hydroxy-5-(hydroxymethyl)oxolan-2-yl]-1,2-dihydropyrimidin-2-one'Doc_130885","h_idx":2,"t_idx":1,"r":"P17"},{"title":"b'4-amino-1-[(2R,4S,5R)-4-hydroxy-5-(hydroxymethyl)oxolan-2-yl]-1,2-dihydropyrimidin-2-one'Doc_130885","h_idx":14,"t_idx":2,"r":"P17"},{"title":"b'4-amino-1-[(2R,4S,5R)-4-hydroxy-5-(hydroxymethyl)oxolan-2-yl]-1,2-dihydropyrimidin-2-one'Doc_130956","h_idx":2,"t_idx":8,"r":"P17"},{"title":"b'4-amino-1-[(2R,4S,5R)-4-hydroxy-5-(hydroxymethyl)oxolan-2-yl]-1,2-dihydropyrimidin-2-one'Doc_130956","h_idx":8,"t_idx":2,"r":"P17"},{"title":"b'4-amino-1-[(2R,4S,5R)-4-hydroxy-5-(hydroxymethyl)oxolan-2-yl]-1,2-dihydropyrimidin-2-one'Doc_130958","h_idx":5,"t_idx":6,"r":"P17"},{"title":"b'4-amino-1-[(2R,4S,5R)-4-hydroxy-5-(hydroxymethyl)oxolan-2-yl]-1,2-dihydropyrimidin-2-one'Doc_130958","h_idx":8,"t_idx":6,"r":"P17"},{"title":"b'Cortexolone'Doc_130975","h_idx":2,"t_idx":1,"r":"P17"},{"title":"b'Cortexolone'Doc_130975","h_idx":14,"t_idx":2,"r":"P17"},{"title":"b'Cortexolone'Doc_131046","h_idx":2,"t_idx":8,"r":"P17"},{"title":"b'Cortexolone'Doc_131046","h_idx":8,"t_idx":2,"r":"P17"},{"title":"b'Cortexolone'Doc_131048","h_idx":5,"t_idx":6,"r":"P17"},{"title":"b'Cortexolone'Doc_131048","h_idx":8,"t_idx":6,"r":"P17"},{"title":"b'(1S,2R,10R,11S,14R,15S)-14-hydroxy-14-(2-hydroxyacetyl)-2,15-dimethyltetracyclo[8.7.0.0^{2,7}.0^{11,15}]heptadec-6-en-5-one'Doc_131065","h_idx":2,"t_idx":1,"r":"P17"},{"title":"b'(1S,2R,10R,11S,14R,15S)-14-hydroxy-14-(2-hydroxyacetyl)-2,15-dimethyltetracyclo[8.7.0.0^{2,7}.0^{11,15}]heptadec-6-en-5-one'Doc_131065","h_idx":14,"t_idx":2,"r":"P17"},{"title":"b'(1S,2R,10R,11S,14R,15S)-14-hydroxy-14-(2-hydroxyacetyl)-2,15-dimethyltetracyclo[8.7.0.0^{2,7}.0^{11,15}]heptadec-6-en-5-one'Doc_131136","h_idx":2,"t_idx":8,"r":"P17"},{"title":"b'(1S,2R,10R,11S,14R,15S)-14-hydroxy-14-(2-hydroxyacetyl)-2,15-dimethyltetracyclo[8.7.0.0^{2,7}.0^{11,15}]heptadec-6-en-5-one'Doc_131136","h_idx":8,"t_idx":2,"r":"P17"},{"title":"b'(1S,2R,10R,11S,14R,15S)-14-hydroxy-14-(2-hydroxyacetyl)-2,15-dimethyltetracyclo[8.7.0.0^{2,7}.0^{11,15}]heptadec-6-en-5-one'Doc_131138","h_idx":5,"t_idx":6,"r":"P17"},{"title":"b'(1S,2R,10R,11S,14R,15S)-14-hydroxy-14-(2-hydroxyacetyl)-2,15-dimethyltetracyclo[8.7.0.0^{2,7}.0^{11,15}]heptadec-6-en-5-one'Doc_131138","h_idx":8,"t_idx":6,"r":"P17"},{"title":"b'Deoxycorticosterone'Doc_131155","h_idx":2,"t_idx":1,"r":"P17"},{"title":"b'Deoxycorticosterone'Doc_131155","h_idx":14,"t_idx":2,"r":"P17"},{"title":"b'Deoxycorticosterone'Doc_131226","h_idx":2,"t_idx":8,"r":"P17"},{"title":"b'Deoxycorticosterone'Doc_131226","h_idx":8,"t_idx":2,"r":"P17"},{"title":"b'Deoxycorticosterone'Doc_131228","h_idx":5,"t_idx":6,"r":"P17"},{"title":"b'Deoxycorticosterone'Doc_131228","h_idx":8,"t_idx":6,"r":"P17"},{"title":"b'(1S,2R,10S,11S,14S,15S)-14-(2-hydroxyacetyl)-2,15-dimethyltetracyclo[8.7.0.0^{2,7}.0^{11,15}]heptadec-6-en-5-one'Doc_131245","h_idx":2,"t_idx":1,"r":"P17"},{"title":"b'(1S,2R,10S,11S,14S,15S)-14-(2-hydroxyacetyl)-2,15-dimethyltetracyclo[8.7.0.0^{2,7}.0^{11,15}]heptadec-6-en-5-one'Doc_131245","h_idx":14,"t_idx":2,"r":"P17"},{"title":"b'(1S,2R,10S,11S,14S,15S)-14-(2-hydroxyacetyl)-2,15-dimethyltetracyclo[8.7.0.0^{2,7}.0^{11,15}]heptadec-6-en-5-one'Doc_131316","h_idx":2,"t_idx":8,"r":"P17"},{"title":"b'(1S,2R,10S,11S,14S,15S)-14-(2-hydroxyacetyl)-2,15-dimethyltetracyclo[8.7.0.0^{2,7}.0^{11,15}]heptadec-6-en-5-one'Doc_131316","h_idx":8,"t_idx":2,"r":"P17"},{"title":"b'(1S,2R,10S,11S,14S,15S)-14-(2-hydroxyacetyl)-2,15-dimethyltetracyclo[8.7.0.0^{2,7}.0^{11,15}]heptadec-6-en-5-one'Doc_131318","h_idx":5,"t_idx":6,"r":"P17"},{"title":"b'(1S,2R,10S,11S,14S,15S)-14-(2-hydroxyacetyl)-2,15-dimethyltetracyclo[8.7.0.0^{2,7}.0^{11,15}]heptadec-6-en-5-one'Doc_131318","h_idx":8,"t_idx":6,"r":"P17"},{"title":"b'4-Pyridoxic acid'Doc_131343","h_idx":5,"t_idx":6,"r":"P17"},{"title":"b'4-Pyridoxic acid'Doc_131343","h_idx":8,"t_idx":6,"r":"P17"},{"title":"b'4-Pyridoxic acid'Doc_131348","h_idx":2,"t_idx":1,"r":"P17"},{"title":"b'4-Pyridoxic acid'Doc_131348","h_idx":14,"t_idx":2,"r":"P17"},{"title":"b'4-Pyridoxic acid'Doc_131387","h_idx":2,"t_idx":8,"r":"P17"},{"title":"b'4-Pyridoxic acid'Doc_131387","h_idx":8,"t_idx":2,"r":"P17"},{"title":"b'3-hydroxy-5-(hydroxymethyl)-2-methylpyridine-4-carboxylic acid'Doc_131432","h_idx":5,"t_idx":6,"r":"P17"},{"title":"b'3-hydroxy-5-(hydroxymethyl)-2-methylpyridine-4-carboxylic acid'Doc_131432","h_idx":8,"t_idx":6,"r":"P17"},{"title":"b'3-hydroxy-5-(hydroxymethyl)-2-methylpyridine-4-carboxylic acid'Doc_131437","h_idx":2,"t_idx":1,"r":"P17"},{"title":"b'3-hydroxy-5-(hydroxymethyl)-2-methylpyridine-4-carboxylic acid'Doc_131437","h_idx":14,"t_idx":2,"r":"P17"},{"title":"b'3-hydroxy-5-(hydroxymethyl)-2-methylpyridine-4-carboxylic acid'Doc_131476","h_idx":2,"t_idx":8,"r":"P17"},{"title":"b'3-hydroxy-5-(hydroxymethyl)-2-methylpyridine-4-carboxylic acid'Doc_131476","h_idx":8,"t_idx":2,"r":"P17"},{"title":"b'alpha-Ketoisovaleric acid'Doc_131562","h_idx":5,"t_idx":6,"r":"P17"},{"title":"b'alpha-Ketoisovaleric acid'Doc_131562","h_idx":8,"t_idx":6,"r":"P17"},{"title":"b'alpha-Ketoisovaleric acid'Doc_131589","h_idx":2,"t_idx":8,"r":"P17"},{"title":"b'alpha-Ketoisovaleric acid'Doc_131589","h_idx":8,"t_idx":2,"r":"P17"},{"title":"b'alpha-Ketoisovaleric acid'Doc_131598","h_idx":2,"t_idx":1,"r":"P17"},{"title":"b'alpha-Ketoisovaleric acid'Doc_131598","h_idx":14,"t_idx":2,"r":"P17"},{"title":"b'3-methyl-2-oxobutanoic acid'Doc_131613","h_idx":5,"t_idx":6,"r":"P17"},{"title":"b'3-methyl-2-oxobutanoic acid'Doc_131613","h_idx":8,"t_idx":6,"r":"P17"},{"title":"b'3-methyl-2-oxobutanoic acid'Doc_131638","h_idx":9,"t_idx":4,"r":"P17"},{"title":"b'3-methyl-2-oxobutanoic acid'Doc_131656","h_idx":2,"t_idx":1,"r":"P17"},{"title":"b'3-methyl-2-oxobutanoic acid'Doc_131656","h_idx":14,"t_idx":2,"r":"P17"},{"title":"b'3-methyl-2-oxobutanoic acid'Doc_131688","h_idx":2,"t_idx":8,"r":"P17"},{"title":"b'3-methyl-2-oxobutanoic acid'Doc_131688","h_idx":8,"t_idx":2,"r":"P17"},{"title":"b'p-Hydroxyphenylacetic acid'Doc_131707","h_idx":5,"t_idx":6,"r":"P17"},{"title":"b'p-Hydroxyphenylacetic acid'Doc_131707","h_idx":8,"t_idx":6,"r":"P17"},{"title":"b'p-Hydroxyphenylacetic acid'Doc_131720","h_idx":2,"t_idx":1,"r":"P17"},{"title":"b'p-Hydroxyphenylacetic acid'Doc_131720","h_idx":14,"t_idx":2,"r":"P17"},{"title":"b'p-Hydroxyphenylacetic acid'Doc_131749","h_idx":9,"t_idx":4,"r":"P17"},{"title":"b'p-Hydroxyphenylacetic acid'Doc_131781","h_idx":2,"t_idx":8,"r":"P17"},{"title":"b'p-Hydroxyphenylacetic acid'Doc_131781","h_idx":8,"t_idx":2,"r":"P17"},{"title":"b'2-(4-hydroxyphenyl)acetic acid'Doc_131798","h_idx":5,"t_idx":6,"r":"P17"},{"title":"b'2-(4-hydroxyphenyl)acetic acid'Doc_131798","h_idx":8,"t_idx":6,"r":"P17"},{"title":"b'2-(4-hydroxyphenyl)acetic acid'Doc_131811","h_idx":2,"t_idx":1,"r":"P17"},{"title":"b'2-(4-hydroxyphenyl)acetic acid'Doc_131811","h_idx":14,"t_idx":2,"r":"P17"},{"title":"b'2-(4-hydroxyphenyl)acetic acid'Doc_131840","h_idx":9,"t_idx":4,"r":"P17"},{"title":"b'2-(4-hydroxyphenyl)acetic acid'Doc_131872","h_idx":2,"t_idx":8,"r":"P17"},{"title":"b'2-(4-hydroxyphenyl)acetic acid'Doc_131872","h_idx":8,"t_idx":2,"r":"P17"},{"title":"b'Iodotyrosine'Doc_131889","h_idx":5,"t_idx":6,"r":"P17"},{"title":"b'Iodotyrosine'Doc_131889","h_idx":8,"t_idx":6,"r":"P17"},{"title":"b'Iodotyrosine'Doc_131902","h_idx":2,"t_idx":1,"r":"P17"},{"title":"b'Iodotyrosine'Doc_131902","h_idx":14,"t_idx":2,"r":"P17"},{"title":"b'Iodotyrosine'Doc_131931","h_idx":9,"t_idx":4,"r":"P17"},{"title":"b'Iodotyrosine'Doc_131963","h_idx":2,"t_idx":8,"r":"P17"},{"title":"b'Iodotyrosine'Doc_131963","h_idx":8,"t_idx":2,"r":"P17"},{"title":"b'(2S)-2-amino-3-(4-hydroxy-3-iodophenyl)propanoic acid'Doc_131980","h_idx":5,"t_idx":6,"r":"P17"},{"title":"b'(2S)-2-amino-3-(4-hydroxy-3-iodophenyl)propanoic acid'Doc_131980","h_idx":8,"t_idx":6,"r":"P17"},{"title":"b'(2S)-2-amino-3-(4-hydroxy-3-iodophenyl)propanoic acid'Doc_131993","h_idx":2,"t_idx":1,"r":"P17"},{"title":"b'(2S)-2-amino-3-(4-hydroxy-3-iodophenyl)propanoic acid'Doc_131993","h_idx":14,"t_idx":2,"r":"P17"},{"title":"b'(2S)-2-amino-3-(4-hydroxy-3-iodophenyl)propanoic acid'Doc_132022","h_idx":9,"t_idx":4,"r":"P17"},{"title":"b'(2S)-2-amino-3-(4-hydroxy-3-iodophenyl)propanoic acid'Doc_132054","h_idx":2,"t_idx":8,"r":"P17"},{"title":"b'(2S)-2-amino-3-(4-hydroxy-3-iodophenyl)propanoic acid'Doc_132054","h_idx":8,"t_idx":2,"r":"P17"},{"title":"b'3-Methoxytyramine'Doc_132071","h_idx":5,"t_idx":6,"r":"P17"},{"title":"b'3-Methoxytyramine'Doc_132071","h_idx":8,"t_idx":6,"r":"P17"},{"title":"b'3-Methoxytyramine'Doc_132084","h_idx":2,"t_idx":1,"r":"P17"},{"title":"b'3-Methoxytyramine'Doc_132084","h_idx":14,"t_idx":2,"r":"P17"},{"title":"b'3-Methoxytyramine'Doc_132113","h_idx":9,"t_idx":4,"r":"P17"},{"title":"b'3-Methoxytyramine'Doc_132145","h_idx":2,"t_idx":8,"r":"P17"},{"title":"b'3-Methoxytyramine'Doc_132145","h_idx":8,"t_idx":2,"r":"P17"},{"title":"b'4-(2-aminoethyl)-2-methoxyphenol'Doc_132162","h_idx":5,"t_idx":6,"r":"P17"},{"title":"b'4-(2-aminoethyl)-2-methoxyphenol'Doc_132162","h_idx":8,"t_idx":6,"r":"P17"},{"title":"b'4-(2-aminoethyl)-2-methoxyphenol'Doc_132175","h_idx":2,"t_idx":1,"r":"P17"},{"title":"b'4-(2-aminoethyl)-2-methoxyphenol'Doc_132175","h_idx":14,"t_idx":2,"r":"P17"},{"title":"b'4-(2-aminoethyl)-2-methoxyphenol'Doc_132204","h_idx":9,"t_idx":4,"r":"P17"},{"title":"b'4-(2-aminoethyl)-2-methoxyphenol'Doc_132236","h_idx":2,"t_idx":8,"r":"P17"},{"title":"b'4-(2-aminoethyl)-2-methoxyphenol'Doc_132236","h_idx":8,"t_idx":2,"r":"P17"},{"title":"b'(S)-3-Hydroxyisobutyric acid'Doc_132253","h_idx":5,"t_idx":6,"r":"P17"},{"title":"b'(S)-3-Hydroxyisobutyric acid'Doc_132253","h_idx":8,"t_idx":6,"r":"P17"},{"title":"b'(S)-3-Hydroxyisobutyric acid'Doc_132266","h_idx":2,"t_idx":1,"r":"P17"},{"title":"b'(S)-3-Hydroxyisobutyric acid'Doc_132266","h_idx":14,"t_idx":2,"r":"P17"},{"title":"b'(S)-3-Hydroxyisobutyric acid'Doc_132295","h_idx":9,"t_idx":4,"r":"P17"},{"title":"b'(S)-3-Hydroxyisobutyric acid'Doc_132327","h_idx":2,"t_idx":8,"r":"P17"},{"title":"b'(S)-3-Hydroxyisobutyric acid'Doc_132327","h_idx":8,"t_idx":2,"r":"P17"},{"title":"b'(2S)-3-hydroxy-2-methylpropanoic acid'Doc_132344","h_idx":5,"t_idx":6,"r":"P17"},{"title":"b'(2S)-3-hydroxy-2-methylpropanoic acid'Doc_132344","h_idx":8,"t_idx":6,"r":"P17"},{"title":"b'(2S)-3-hydroxy-2-methylpropanoic acid'Doc_132357","h_idx":2,"t_idx":1,"r":"P17"},{"title":"b'(2S)-3-hydroxy-2-methylpropanoic acid'Doc_132357","h_idx":14,"t_idx":2,"r":"P17"},{"title":"b'(2S)-3-hydroxy-2-methylpropanoic acid'Doc_132386","h_idx":9,"t_idx":4,"r":"P17"},{"title":"b'(2S)-3-hydroxy-2-methylpropanoic acid'Doc_132418","h_idx":2,"t_idx":8,"r":"P17"},{"title":"b'(2S)-3-hydroxy-2-methylpropanoic acid'Doc_132418","h_idx":8,"t_idx":2,"r":"P17"},{"title":"b'3-O-Sulfogalactosylceramide (d18:1\/24:0)'Doc_132456","h_idx":3,"t_idx":2,"r":"P17"},{"title":"b'3-O-Sulfogalactosylceramide (d18:1\/24:0)'Doc_132468","h_idx":2,"t_idx":3,"r":"P17"},{"title":"b'3-O-Sulfogalactosylceramide (d18:1\/24:0)'Doc_132468","h_idx":3,"t_idx":2,"r":"P17"},{"title":"b'3-O-Sulfogalactosylceramide (d18:1\/24:0)'Doc_132471","h_idx":7,"t_idx":1,"r":"P17"},{"title":"b'3-O-Sulfogalactosylceramide (d18:1\/24:0)'Doc_132471","h_idx":7,"t_idx":6,"r":"P17"},{"title":"b'3-O-Sulfogalactosylceramide (d18:1\/24:0)'Doc_132483","h_idx":18,"t_idx":10,"r":"P17"},{"title":"b'3-O-Sulfogalactosylceramide (d18:1\/24:0)'Doc_132494","h_idx":6,"t_idx":7,"r":"P17"},{"title":"b'[(2R,5S,6R)-3,5-dihydroxy-2-{[(2S,3R,4E)-3-hydroxy-2-tetracosanamidooctadec-4-en-1-yl]oxy}-6-(hydroxymethyl)oxan-4-yl]oxidanesulfonic acid'Doc_132533","h_idx":3,"t_idx":2,"r":"P17"},{"title":"b'[(2R,5S,6R)-3,5-dihydroxy-2-{[(2S,3R,4E)-3-hydroxy-2-tetracosanamidooctadec-4-en-1-yl]oxy}-6-(hydroxymethyl)oxan-4-yl]oxidanesulfonic acid'Doc_132545","h_idx":2,"t_idx":3,"r":"P17"},{"title":"b'[(2R,5S,6R)-3,5-dihydroxy-2-{[(2S,3R,4E)-3-hydroxy-2-tetracosanamidooctadec-4-en-1-yl]oxy}-6-(hydroxymethyl)oxan-4-yl]oxidanesulfonic acid'Doc_132545","h_idx":3,"t_idx":2,"r":"P17"},{"title":"b'[(2R,5S,6R)-3,5-dihydroxy-2-{[(2S,3R,4E)-3-hydroxy-2-tetracosanamidooctadec-4-en-1-yl]oxy}-6-(hydroxymethyl)oxan-4-yl]oxidanesulfonic acid'Doc_132548","h_idx":7,"t_idx":1,"r":"P17"},{"title":"b'[(2R,5S,6R)-3,5-dihydroxy-2-{[(2S,3R,4E)-3-hydroxy-2-tetracosanamidooctadec-4-en-1-yl]oxy}-6-(hydroxymethyl)oxan-4-yl]oxidanesulfonic acid'Doc_132548","h_idx":7,"t_idx":6,"r":"P17"},{"title":"b'[(2R,5S,6R)-3,5-dihydroxy-2-{[(2S,3R,4E)-3-hydroxy-2-tetracosanamidooctadec-4-en-1-yl]oxy}-6-(hydroxymethyl)oxan-4-yl]oxidanesulfonic acid'Doc_132560","h_idx":18,"t_idx":10,"r":"P17"},{"title":"b'[(2R,5S,6R)-3,5-dihydroxy-2-{[(2S,3R,4E)-3-hydroxy-2-tetracosanamidooctadec-4-en-1-yl]oxy}-6-(hydroxymethyl)oxan-4-yl]oxidanesulfonic acid'Doc_132571","h_idx":6,"t_idx":7,"r":"P17"},{"title":"b'Ureidopropionic acid'Doc_132576","h_idx":5,"t_idx":6,"r":"P17"},{"title":"b'Ureidopropionic acid'Doc_132576","h_idx":8,"t_idx":6,"r":"P17"},{"title":"b'Ureidopropionic acid'Doc_132616","h_idx":2,"t_idx":1,"r":"P17"},{"title":"b'Ureidopropionic acid'Doc_132616","h_idx":14,"t_idx":2,"r":"P17"},{"title":"b'Ureidopropionic acid'Doc_132635","h_idx":2,"t_idx":8,"r":"P17"},{"title":"b'Ureidopropionic acid'Doc_132635","h_idx":8,"t_idx":2,"r":"P17"},{"title":"b'3-(carbamoylamino)propanoic acid'Doc_132666","h_idx":5,"t_idx":6,"r":"P17"},{"title":"b'3-(carbamoylamino)propanoic acid'Doc_132666","h_idx":8,"t_idx":6,"r":"P17"},{"title":"b'3-(carbamoylamino)propanoic acid'Doc_132706","h_idx":2,"t_idx":1,"r":"P17"},{"title":"b'3-(carbamoylamino)propanoic acid'Doc_132706","h_idx":14,"t_idx":2,"r":"P17"},{"title":"b'3-(carbamoylamino)propanoic acid'Doc_132725","h_idx":2,"t_idx":8,"r":"P17"},{"title":"b'3-(carbamoylamino)propanoic acid'Doc_132725","h_idx":8,"t_idx":2,"r":"P17"},{"title":"b'Tetrahydrobiopterin'Doc_132756","h_idx":5,"t_idx":6,"r":"P17"},{"title":"b'Tetrahydrobiopterin'Doc_132756","h_idx":8,"t_idx":6,"r":"P17"},{"title":"b'Tetrahydrobiopterin'Doc_132796","h_idx":2,"t_idx":1,"r":"P17"},{"title":"b'Tetrahydrobiopterin'Doc_132796","h_idx":14,"t_idx":2,"r":"P17"},{"title":"b'Tetrahydrobiopterin'Doc_132815","h_idx":2,"t_idx":8,"r":"P17"},{"title":"b'Tetrahydrobiopterin'Doc_132815","h_idx":8,"t_idx":2,"r":"P17"},{"title":"b'(6R)-2-amino-6-[(1R,2S)-1,2-dihydroxypropyl]-1,4,5,6,7,8-hexahydropteridin-4-one'Doc_132846","h_idx":5,"t_idx":6,"r":"P17"},{"title":"b'(6R)-2-amino-6-[(1R,2S)-1,2-dihydroxypropyl]-1,4,5,6,7,8-hexahydropteridin-4-one'Doc_132846","h_idx":8,"t_idx":6,"r":"P17"},{"title":"b'(6R)-2-amino-6-[(1R,2S)-1,2-dihydroxypropyl]-1,4,5,6,7,8-hexahydropteridin-4-one'Doc_132886","h_idx":2,"t_idx":1,"r":"P17"},{"title":"b'(6R)-2-amino-6-[(1R,2S)-1,2-dihydroxypropyl]-1,4,5,6,7,8-hexahydropteridin-4-one'Doc_132886","h_idx":14,"t_idx":2,"r":"P17"},{"title":"b'(6R)-2-amino-6-[(1R,2S)-1,2-dihydroxypropyl]-1,4,5,6,7,8-hexahydropteridin-4-one'Doc_132905","h_idx":2,"t_idx":8,"r":"P17"},{"title":"b'(6R)-2-amino-6-[(1R,2S)-1,2-dihydroxypropyl]-1,4,5,6,7,8-hexahydropteridin-4-one'Doc_132905","h_idx":8,"t_idx":2,"r":"P17"},{"title":"b'Biotin'Doc_132962","h_idx":0,"t_idx":5,"r":"P17"},{"title":"b'Biotin'Doc_132962","h_idx":18,"t_idx":5,"r":"P17"},{"title":"b'5-[(3aS,4S,6aR)-2-oxo-hexahydro-1H-thieno[3,4-d]imidazol-4-yl]pentanoic acid'Doc_132998","h_idx":0,"t_idx":5,"r":"P17"},{"title":"b'5-[(3aS,4S,6aR)-2-oxo-hexahydro-1H-thieno[3,4-d]imidazol-4-yl]pentanoic acid'Doc_132998","h_idx":18,"t_idx":5,"r":"P17"},{"title":"b'Androsterone'Doc_133034","h_idx":0,"t_idx":5,"r":"P17"},{"title":"b'Androsterone'Doc_133034","h_idx":18,"t_idx":5,"r":"P17"},{"title":"b'(1S,2S,5R,7S,10R,11S,15S)-5-hydroxy-2,15-dimethyltetracyclo[8.7.0.0^{2,7}.0^{11,15}]heptadecan-14-one'Doc_133070","h_idx":0,"t_idx":5,"r":"P17"},{"title":"b'(1S,2S,5R,7S,10R,11S,15S)-5-hydroxy-2,15-dimethyltetracyclo[8.7.0.0^{2,7}.0^{11,15}]heptadecan-14-one'Doc_133070","h_idx":18,"t_idx":5,"r":"P17"},{"title":"b'7-Dehydrocholesterol'Doc_133106","h_idx":0,"t_idx":5,"r":"P17"},{"title":"b'7-Dehydrocholesterol'Doc_133106","h_idx":18,"t_idx":5,"r":"P17"},{"title":"b'(1S,2R,5S,11R,14R,15R)-2,15-dimethyl-14-[(2R)-6-methylheptan-2-yl]tetracyclo[8.7.0.0^{2,7}.0^{11,15}]heptadeca-7,9-dien-5-ol'Doc_133142","h_idx":0,"t_idx":5,"r":"P17"},{"title":"b'(1S,2R,5S,11R,14R,15R)-2,15-dimethyl-14-[(2R)-6-methylheptan-2-yl]tetracyclo[8.7.0.0^{2,7}.0^{11,15}]heptadeca-7,9-dien-5-ol'Doc_133142","h_idx":18,"t_idx":5,"r":"P17"},{"title":"b'Carnosine'Doc_133159","h_idx":9,"t_idx":10,"r":"P17"},{"title":"b'Carnosine'Doc_133159","h_idx":14,"t_idx":10,"r":"P17"},{"title":"b'Carnosine'Doc_133168","h_idx":2,"t_idx":14,"r":"P17"},{"title":"b'Carnosine'Doc_133176","h_idx":2,"t_idx":1,"r":"P17"},{"title":"b'Carnosine'Doc_133199","h_idx":12,"t_idx":20,"r":"P17"},{"title":"b'Carnosine'Doc_133233","h_idx":3,"t_idx":0,"r":"P17"},{"title":"b'(2S)-2-(3-aminopropanamido)-3-(1H-imidazol-5-yl)propanoic acid'Doc_133247","h_idx":9,"t_idx":10,"r":"P17"},{"title":"b'(2S)-2-(3-aminopropanamido)-3-(1H-imidazol-5-yl)propanoic acid'Doc_133247","h_idx":14,"t_idx":10,"r":"P17"},{"title":"b'(2S)-2-(3-aminopropanamido)-3-(1H-imidazol-5-yl)propanoic acid'Doc_133256","h_idx":2,"t_idx":14,"r":"P17"},{"title":"b'(2S)-2-(3-aminopropanamido)-3-(1H-imidazol-5-yl)propanoic acid'Doc_133264","h_idx":2,"t_idx":1,"r":"P17"},{"title":"b'(2S)-2-(3-aminopropanamido)-3-(1H-imidazol-5-yl)propanoic acid'Doc_133287","h_idx":12,"t_idx":20,"r":"P17"},{"title":"b'(2S)-2-(3-aminopropanamido)-3-(1H-imidazol-5-yl)propanoic acid'Doc_133321","h_idx":3,"t_idx":0,"r":"P17"},{"title":"b'(2S)-2-(3-aminopropanamido)-3-(1H-imidazol-5-yl)propanoic acid'Doc_133326","h_idx":12,"t_idx":5,"r":"P17"},{"title":"b'Adenine'Doc_133338","h_idx":5,"t_idx":8,"r":"P17"},{"title":"b'Adenine'Doc_133338","h_idx":5,"t_idx":10,"r":"P17"},{"title":"b'Adenine'Doc_133338","h_idx":6,"t_idx":8,"r":"P17"},{"title":"b'Adenine'Doc_133338","h_idx":6,"t_idx":10,"r":"P17"},{"title":"b'Adenine'Doc_133347","h_idx":13,"t_idx":14,"r":"P17"},{"title":"b'Adenine'Doc_133347","h_idx":20,"t_idx":33,"r":"P17"},{"title":"b'Adenine'Doc_133347","h_idx":33,"t_idx":20,"r":"P17"},{"title":"b'Adenine'Doc_133357","h_idx":9,"t_idx":8,"r":"P17"},{"title":"b'Adenine'Doc_133360","h_idx":13,"t_idx":12,"r":"P17"},{"title":"b'Adenine'Doc_133366","h_idx":1,"t_idx":3,"r":"P17"},{"title":"b'Adenine'Doc_133377","h_idx":2,"t_idx":12,"r":"P17"},{"title":"b'Adenine'Doc_133387","h_idx":0,"t_idx":28,"r":"P17"},{"title":"b'Adenine'Doc_133387","h_idx":78,"t_idx":23,"r":"P17"},{"title":"b'Adenine'Doc_133392","h_idx":25,"t_idx":11,"r":"P17"},{"title":"b'Adenine'Doc_133393","h_idx":12,"t_idx":18,"r":"P17"},{"title":"b'Adenine'Doc_133394","h_idx":16,"t_idx":18,"r":"P17"},{"title":"b'Adenine'Doc_133399","h_idx":2,"t_idx":22,"r":"P17"},{"title":"b'Adenine'Doc_133405","h_idx":16,"t_idx":20,"r":"P17"},{"title":"b'Adenine'Doc_133421","h_idx":50,"t_idx":0,"r":"P17"},{"title":"b'Adenine'Doc_133421","h_idx":50,"t_idx":2,"r":"P17"},{"title":"b'Adenine'Doc_133421","h_idx":50,"t_idx":20,"r":"P17"},{"title":"b'Adenine'Doc_133421","h_idx":50,"t_idx":22,"r":"P17"},{"title":"b'7H-purin-6-amine'Doc_133437","h_idx":12,"t_idx":11,"r":"P17"},{"title":"b'7H-purin-6-amine'Doc_133437","h_idx":23,"t_idx":0,"r":"P17"},{"title":"b'7H-purin-6-amine'Doc_133438","h_idx":6,"t_idx":2,"r":"P17"},{"title":"b'7H-purin-6-amine'Doc_133444","h_idx":8,"t_idx":37,"r":"P17"},{"title":"b'7H-purin-6-amine'Doc_133444","h_idx":50,"t_idx":2,"r":"P17"},{"title":"b'7H-purin-6-amine'Doc_133448","h_idx":31,"t_idx":21,"r":"P17"},{"title":"b'7H-purin-6-amine'Doc_133462","h_idx":42,"t_idx":11,"r":"P17"},{"title":"b'7H-purin-6-amine'Doc_133471","h_idx":25,"t_idx":14,"r":"P17"},{"title":"b'7H-purin-6-amine'Doc_133480","h_idx":15,"t_idx":22,"r":"P17"},{"title":"b'7H-purin-6-amine'Doc_133482","h_idx":34,"t_idx":13,"r":"P17"},{"title":"b'7H-purin-6-amine'Doc_133482","h_idx":38,"t_idx":82,"r":"P17"},{"title":"b'7H-purin-6-amine'Doc_133482","h_idx":44,"t_idx":65,"r":"P17"},{"title":"b'7H-purin-6-amine'Doc_133482","h_idx":77,"t_idx":81,"r":"P17"},{"title":"b'7H-purin-6-amine'Doc_133490","h_idx":5,"t_idx":0,"r":"P17"},{"title":"b'7H-purin-6-amine'Doc_133508","h_idx":27,"t_idx":1,"r":"P17"},{"title":"b'7H-purin-6-amine'Doc_133509","h_idx":4,"t_idx":4,"r":"P17"},{"title":"b'7H-purin-6-amine'Doc_133510","h_idx":10,"t_idx":22,"r":"P17"},{"title":"b'7H-purin-6-amine'Doc_133510","h_idx":11,"t_idx":24,"r":"P17"},{"title":"b'7H-purin-6-amine'Doc_133513","h_idx":3,"t_idx":24,"r":"P17"},{"title":"b'7H-purin-6-amine'Doc_133513","h_idx":6,"t_idx":0,"r":"P17"},{"title":"b'Taurocholic acid'Doc_133563","h_idx":21,"t_idx":9,"r":"P17"},{"title":"b'Taurocholic acid'Doc_133567","h_idx":1,"t_idx":9,"r":"P17"},{"title":"b'Taurocholic acid'Doc_133576","h_idx":8,"t_idx":10,"r":"P17"},{"title":"b'Taurocholic acid'Doc_133576","h_idx":10,"t_idx":4,"r":"P17"},{"title":"b'Taurocholic acid'Doc_133587","h_idx":24,"t_idx":3,"r":"P17"},{"title":"b'Taurocholic acid'Doc_133588","h_idx":0,"t_idx":11,"r":"P17"},{"title":"b'2-[(4R)-4-[(1S,2S,5R,7S,9R,10R,11S,14R,15R,16S)-5,9,16-trihydroxy-2,15-dimethyltetracyclo[8.7.0.0^{2,7}.0^{11,15}]heptadecan-14-yl]pentanamido]ethane-1-sulfonic acid'Doc_133654","h_idx":21,"t_idx":9,"r":"P17"},{"title":"b'2-[(4R)-4-[(1S,2S,5R,7S,9R,10R,11S,14R,15R,16S)-5,9,16-trihydroxy-2,15-dimethyltetracyclo[8.7.0.0^{2,7}.0^{11,15}]heptadecan-14-yl]pentanamido]ethane-1-sulfonic acid'Doc_133658","h_idx":1,"t_idx":9,"r":"P17"},{"title":"b'2-[(4R)-4-[(1S,2S,5R,7S,9R,10R,11S,14R,15R,16S)-5,9,16-trihydroxy-2,15-dimethyltetracyclo[8.7.0.0^{2,7}.0^{11,15}]heptadecan-14-yl]pentanamido]ethane-1-sulfonic acid'Doc_133667","h_idx":8,"t_idx":10,"r":"P17"},{"title":"b'2-[(4R)-4-[(1S,2S,5R,7S,9R,10R,11S,14R,15R,16S)-5,9,16-trihydroxy-2,15-dimethyltetracyclo[8.7.0.0^{2,7}.0^{11,15}]heptadecan-14-yl]pentanamido]ethane-1-sulfonic acid'Doc_133667","h_idx":10,"t_idx":4,"r":"P17"},{"title":"b'2-[(4R)-4-[(1S,2S,5R,7S,9R,10R,11S,14R,15R,16S)-5,9,16-trihydroxy-2,15-dimethyltetracyclo[8.7.0.0^{2,7}.0^{11,15}]heptadecan-14-yl]pentanamido]ethane-1-sulfonic acid'Doc_133678","h_idx":24,"t_idx":3,"r":"P17"},{"title":"b'2-[(4R)-4-[(1S,2S,5R,7S,9R,10R,11S,14R,15R,16S)-5,9,16-trihydroxy-2,15-dimethyltetracyclo[8.7.0.0^{2,7}.0^{11,15}]heptadecan-14-yl]pentanamido]ethane-1-sulfonic acid'Doc_133679","h_idx":0,"t_idx":11,"r":"P17"},{"title":"b'Aldosterone'Doc_133745","h_idx":21,"t_idx":9,"r":"P17"},{"title":"b'Aldosterone'Doc_133749","h_idx":1,"t_idx":9,"r":"P17"},{"title":"b'Aldosterone'Doc_133758","h_idx":8,"t_idx":10,"r":"P17"},{"title":"b'Aldosterone'Doc_133758","h_idx":10,"t_idx":4,"r":"P17"},{"title":"b'Aldosterone'Doc_133769","h_idx":24,"t_idx":3,"r":"P17"},{"title":"b'Aldosterone'Doc_133770","h_idx":0,"t_idx":11,"r":"P17"},{"title":"b'(1S,2R,10S,11S,14S,15R,17S)-17-hydroxy-14-(2-hydroxyacetyl)-2-methyl-5-oxotetracyclo[8.7.0.0^{2,7}.0^{11,15}]heptadec-6-ene-15-carbaldehyde'Doc_133836","h_idx":21,"t_idx":9,"r":"P17"},{"title":"b'(1S,2R,10S,11S,14S,15R,17S)-17-hydroxy-14-(2-hydroxyacetyl)-2-methyl-5-oxotetracyclo[8.7.0.0^{2,7}.0^{11,15}]heptadec-6-ene-15-carbaldehyde'Doc_133840","h_idx":1,"t_idx":9,"r":"P17"},{"title":"b'(1S,2R,10S,11S,14S,15R,17S)-17-hydroxy-14-(2-hydroxyacetyl)-2-methyl-5-oxotetracyclo[8.7.0.0^{2,7}.0^{11,15}]heptadec-6-ene-15-carbaldehyde'Doc_133849","h_idx":8,"t_idx":10,"r":"P17"},{"title":"b'(1S,2R,10S,11S,14S,15R,17S)-17-hydroxy-14-(2-hydroxyacetyl)-2-methyl-5-oxotetracyclo[8.7.0.0^{2,7}.0^{11,15}]heptadec-6-ene-15-carbaldehyde'Doc_133849","h_idx":10,"t_idx":4,"r":"P17"},{"title":"b'(1S,2R,10S,11S,14S,15R,17S)-17-hydroxy-14-(2-hydroxyacetyl)-2-methyl-5-oxotetracyclo[8.7.0.0^{2,7}.0^{11,15}]heptadec-6-ene-15-carbaldehyde'Doc_133860","h_idx":24,"t_idx":3,"r":"P17"},{"title":"b'(1S,2R,10S,11S,14S,15R,17S)-17-hydroxy-14-(2-hydroxyacetyl)-2-methyl-5-oxotetracyclo[8.7.0.0^{2,7}.0^{11,15}]heptadec-6-ene-15-carbaldehyde'Doc_133861","h_idx":0,"t_idx":11,"r":"P17"},{"title":"b'Dihydrobiopterin'Doc_133927","h_idx":6,"t_idx":18,"r":"P17"},{"title":"b'Dihydrobiopterin'Doc_133927","h_idx":9,"t_idx":0,"r":"P17"},{"title":"b'Dihydrobiopterin'Doc_133942","h_idx":1,"t_idx":6,"r":"P17"},{"title":"b'Dihydrobiopterin'Doc_133942","h_idx":15,"t_idx":11,"r":"P17"},{"title":"b'Dihydrobiopterin'Doc_133945","h_idx":10,"t_idx":11,"r":"P17"},{"title":"b'Dihydrobiopterin'Doc_133945","h_idx":13,"t_idx":5,"r":"P17"},{"title":"b'Butyric acid'Doc_133987","h_idx":7,"t_idx":4,"r":"P17"},{"title":"b'Butyric acid'Doc_133987","h_idx":9,"t_idx":4,"r":"P17"},{"title":"b'Butyric acid'Doc_133990","h_idx":0,"t_idx":0,"r":"P17"},{"title":"b'Butyric acid'Doc_133990","h_idx":4,"t_idx":8,"r":"P17"},{"title":"b'Butyric acid'Doc_134001","h_idx":13,"t_idx":13,"r":"P17"},{"title":"b'Butyric acid'Doc_134002","h_idx":14,"t_idx":4,"r":"P17"},{"title":"b'butanoic acid'Doc_134091","h_idx":10,"t_idx":1,"r":"P17"},{"title":"b'butanoic acid'Doc_134093","h_idx":0,"t_idx":4,"r":"P17"},{"title":"b'butanoic acid'Doc_134104","h_idx":8,"t_idx":6,"r":"P17"},{"title":"b'butanoic acid'Doc_134104","h_idx":18,"t_idx":5,"r":"P17"},{"title":"b'butanoic acid'Doc_134121","h_idx":10,"t_idx":4,"r":"P17"},{"title":"b'butanoic acid'Doc_134122","h_idx":2,"t_idx":11,"r":"P17"},{"title":"b'Acetic acid'Doc_134160","h_idx":9,"t_idx":20,"r":"P17"},{"title":"b'Acetic acid'Doc_134160","h_idx":11,"t_idx":10,"r":"P17"},{"title":"b'Acetic acid'Doc_134187","h_idx":20,"t_idx":10,"r":"P17"},{"title":"b'Acetic acid'Doc_134188","h_idx":5,"t_idx":5,"r":"P17"},{"title":"b'Acetic acid'Doc_134207","h_idx":2,"t_idx":4,"r":"P17"},{"title":"b'Acetic acid'Doc_134208","h_idx":0,"t_idx":1,"r":"P17"},{"title":"b'acetic acid'Doc_134273","h_idx":5,"t_idx":1,"r":"P17"},{"title":"b'acetic acid'Doc_134303","h_idx":8,"t_idx":0,"r":"P17"},{"title":"b'acetic acid'Doc_134303","h_idx":11,"t_idx":10,"r":"P17"},{"title":"b'Betaine'Doc_134390","h_idx":26,"t_idx":19,"r":"P17"},{"title":"b'Betaine'Doc_134411","h_idx":12,"t_idx":29,"r":"P17"},{"title":"b'Betaine'Doc_134422","h_idx":19,"t_idx":23,"r":"P17"},{"title":"b'Betaine'Doc_134422","h_idx":21,"t_idx":17,"r":"P17"},{"title":"b'(carboxymethyl)trimethylazanium'Doc_134486","h_idx":26,"t_idx":19,"r":"P17"},{"title":"b'(carboxymethyl)trimethylazanium'Doc_134499","h_idx":4,"t_idx":34,"r":"P17"},{"title":"b'(carboxymethyl)trimethylazanium'Doc_134499","h_idx":10,"t_idx":29,"r":"P17"},{"title":"b'(carboxymethyl)trimethylazanium'Doc_134518","h_idx":12,"t_idx":15,"r":"P17"},{"title":"b'(carboxymethyl)trimethylazanium'Doc_134518","h_idx":13,"t_idx":25,"r":"P17"},{"title":"b'(carboxymethyl)trimethylazanium'Doc_134521","h_idx":11,"t_idx":19,"r":"P17"},{"title":"b'(carboxymethyl)trimethylazanium'Doc_134521","h_idx":14,"t_idx":7,"r":"P17"},{"title":"b'Ascorbic acid'Doc_134532","h_idx":6,"t_idx":7,"r":"P17"},{"title":"b'Ascorbic acid'Doc_134533","h_idx":12,"t_idx":1,"r":"P17"},{"title":"b'Ascorbic acid'Doc_134586","h_idx":6,"t_idx":2,"r":"P17"},{"title":"b'Ascorbic acid'Doc_134586","h_idx":8,"t_idx":2,"r":"P17"},{"title":"b'Ascorbic acid'Doc_134598","h_idx":4,"t_idx":2,"r":"P17"},{"title":"b'Ascorbic acid'Doc_134598","h_idx":7,"t_idx":2,"r":"P17"},{"title":"b'(2R,3R,4S,5R)-2-(6-amino-9H-purin-9-yl)-5-(hydroxymethyl)oxolane-3,4-diol'Doc_134733","h_idx":50,"t_idx":50,"r":"P17"},{"title":"b'Ammonia'Doc_134791","h_idx":13,"t_idx":20,"r":"P17"},{"title":"b'Ammonia'Doc_134804","h_idx":14,"t_idx":9,"r":"P17"},{"title":"b'ammonia'Doc_134832","h_idx":3,"t_idx":12,"r":"P17"},{"title":"b'ammonia'Doc_134893","h_idx":4,"t_idx":23,"r":"P17"},{"title":"b'ammonia'Doc_134893","h_idx":6,"t_idx":27,"r":"P17"},{"title":"b'ammonia'Doc_134908","h_idx":16,"t_idx":19,"r":"P17"},{"title":"b'ammonia'Doc_134908","h_idx":17,"t_idx":23,"r":"P17"},{"title":"b'ammonia'Doc_134910","h_idx":6,"t_idx":13,"r":"P17"},{"title":"b'ammonia'Doc_134911","h_idx":2,"t_idx":24,"r":"P17"},{"title":"b'Argininosuccinic acid'Doc_134949","h_idx":2,"t_idx":5,"r":"P17"},{"title":"b'Argininosuccinic acid'Doc_134950","h_idx":2,"t_idx":8,"r":"P17"},{"title":"b'Argininosuccinic acid'Doc_134990","h_idx":19,"t_idx":16,"r":"P17"},{"title":"b'Argininosuccinic acid'Doc_134990","h_idx":21,"t_idx":2,"r":"P17"},{"title":"b'Argininosuccinic acid'Doc_134996","h_idx":7,"t_idx":2,"r":"P17"},{"title":"b'Argininosuccinic acid'Doc_134998","h_idx":9,"t_idx":9,"r":"P17"},{"title":"b\"(2S)-2-{N'-[(4S)-4-amino-4-carboxybutyl]carbamimidamido}butanedioic acid\"Doc_135040","h_idx":2,"t_idx":5,"r":"P17"},{"title":"b\"(2S)-2-{N'-[(4S)-4-amino-4-carboxybutyl]carbamimidamido}butanedioic acid\"Doc_135041","h_idx":2,"t_idx":8,"r":"P17"},{"title":"b\"(2S)-2-{N'-[(4S)-4-amino-4-carboxybutyl]carbamimidamido}butanedioic acid\"Doc_135081","h_idx":19,"t_idx":16,"r":"P17"},{"title":"b\"(2S)-2-{N'-[(4S)-4-amino-4-carboxybutyl]carbamimidamido}butanedioic acid\"Doc_135081","h_idx":21,"t_idx":2,"r":"P17"},{"title":"b\"(2S)-2-{N'-[(4S)-4-amino-4-carboxybutyl]carbamimidamido}butanedioic acid\"Doc_135087","h_idx":7,"t_idx":2,"r":"P17"},{"title":"b\"(2S)-2-{N'-[(4S)-4-amino-4-carboxybutyl]carbamimidamido}butanedioic acid\"Doc_135089","h_idx":9,"t_idx":9,"r":"P17"},{"title":"b'Androstenedione'Doc_135131","h_idx":2,"t_idx":5,"r":"P17"},{"title":"b'Androstenedione'Doc_135132","h_idx":2,"t_idx":8,"r":"P17"},{"title":"b'Androstenedione'Doc_135172","h_idx":19,"t_idx":16,"r":"P17"},{"title":"b'Androstenedione'Doc_135172","h_idx":21,"t_idx":2,"r":"P17"},{"title":"b'Androstenedione'Doc_135178","h_idx":7,"t_idx":2,"r":"P17"},{"title":"b'Androstenedione'Doc_135180","h_idx":9,"t_idx":9,"r":"P17"},{"title":"b'(1S,2R,10R,11S,15S)-2,15-dimethyltetracyclo[8.7.0.0^{2,7}.0^{11,15}]heptadec-6-ene-5,14-dione'Doc_135222","h_idx":2,"t_idx":5,"r":"P17"},{"title":"b'(1S,2R,10R,11S,15S)-2,15-dimethyltetracyclo[8.7.0.0^{2,7}.0^{11,15}]heptadec-6-ene-5,14-dione'Doc_135223","h_idx":2,"t_idx":8,"r":"P17"},{"title":"b'(1S,2R,10R,11S,15S)-2,15-dimethyltetracyclo[8.7.0.0^{2,7}.0^{11,15}]heptadec-6-ene-5,14-dione'Doc_135263","h_idx":19,"t_idx":16,"r":"P17"},{"title":"b'(1S,2R,10R,11S,15S)-2,15-dimethyltetracyclo[8.7.0.0^{2,7}.0^{11,15}]heptadec-6-ene-5,14-dione'Doc_135263","h_idx":21,"t_idx":2,"r":"P17"},{"title":"b'(1S,2R,10R,11S,15S)-2,15-dimethyltetracyclo[8.7.0.0^{2,7}.0^{11,15}]heptadec-6-ene-5,14-dione'Doc_135269","h_idx":7,"t_idx":2,"r":"P17"},{"title":"b'(1S,2R,10R,11S,15S)-2,15-dimethyltetracyclo[8.7.0.0^{2,7}.0^{11,15}]heptadec-6-ene-5,14-dione'Doc_135271","h_idx":9,"t_idx":9,"r":"P17"},{"title":"b'Bilirubin'Doc_135313","h_idx":2,"t_idx":5,"r":"P17"},{"title":"b'Bilirubin'Doc_135314","h_idx":2,"t_idx":8,"r":"P17"},{"title":"b'Bilirubin'Doc_135354","h_idx":19,"t_idx":16,"r":"P17"},{"title":"b'Bilirubin'Doc_135354","h_idx":21,"t_idx":2,"r":"P17"},{"title":"b'Bilirubin'Doc_135360","h_idx":7,"t_idx":2,"r":"P17"},{"title":"b'Bilirubin'Doc_135362","h_idx":9,"t_idx":9,"r":"P17"},{"title":"b'3-(2-{[3-(2-carboxyethyl)-5-{[(2Z)-4-ethenyl-3-methyl-5-oxo-2,5-dihydro-1H-pyrrol-2-ylidene]methyl}-4-methyl-1H-pyrrol-2-yl]methyl}-5-{[(2Z)-3-ethenyl-4-methyl-5-oxo-2,5-dihydro-1H-pyrrol-2-ylidene]methyl}-4-methyl-1H-pyrrol-3-yl)propanoic acid'Doc_135404","h_idx":2,"t_idx":5,"r":"P17"},{"title":"b'3-(2-{[3-(2-carboxyethyl)-5-{[(2Z)-4-ethenyl-3-methyl-5-oxo-2,5-dihydro-1H-pyrrol-2-ylidene]methyl}-4-methyl-1H-pyrrol-2-yl]methyl}-5-{[(2Z)-3-ethenyl-4-methyl-5-oxo-2,5-dihydro-1H-pyrrol-2-ylidene]methyl}-4-methyl-1H-pyrrol-3-yl)propanoic acid'Doc_135405","h_idx":2,"t_idx":8,"r":"P17"},{"title":"b'3-(2-{[3-(2-carboxyethyl)-5-{[(2Z)-4-ethenyl-3-methyl-5-oxo-2,5-dihydro-1H-pyrrol-2-ylidene]methyl}-4-methyl-1H-pyrrol-2-yl]methyl}-5-{[(2Z)-3-ethenyl-4-methyl-5-oxo-2,5-dihydro-1H-pyrrol-2-ylidene]methyl}-4-methyl-1H-pyrrol-3-yl)propanoic acid'Doc_135445","h_idx":19,"t_idx":16,"r":"P17"},{"title":"b'3-(2-{[3-(2-carboxyethyl)-5-{[(2Z)-4-ethenyl-3-methyl-5-oxo-2,5-dihydro-1H-pyrrol-2-ylidene]methyl}-4-methyl-1H-pyrrol-2-yl]methyl}-5-{[(2Z)-3-ethenyl-4-methyl-5-oxo-2,5-dihydro-1H-pyrrol-2-ylidene]methyl}-4-methyl-1H-pyrrol-3-yl)propanoic acid'Doc_135445","h_idx":21,"t_idx":2,"r":"P17"},{"title":"b'3-(2-{[3-(2-carboxyethyl)-5-{[(2Z)-4-ethenyl-3-methyl-5-oxo-2,5-dihydro-1H-pyrrol-2-ylidene]methyl}-4-methyl-1H-pyrrol-2-yl]methyl}-5-{[(2Z)-3-ethenyl-4-methyl-5-oxo-2,5-dihydro-1H-pyrrol-2-ylidene]methyl}-4-methyl-1H-pyrrol-3-yl)propanoic acid'Doc_135451","h_idx":7,"t_idx":2,"r":"P17"},{"title":"b'3-(2-{[3-(2-carboxyethyl)-5-{[(2Z)-4-ethenyl-3-methyl-5-oxo-2,5-dihydro-1H-pyrrol-2-ylidene]methyl}-4-methyl-1H-pyrrol-2-yl]methyl}-5-{[(2Z)-3-ethenyl-4-methyl-5-oxo-2,5-dihydro-1H-pyrrol-2-ylidene]methyl}-4-methyl-1H-pyrrol-3-yl)propanoic acid'Doc_135453","h_idx":9,"t_idx":9,"r":"P17"},{"title":"b'Cellobiose'Doc_135495","h_idx":2,"t_idx":5,"r":"P17"},{"title":"b'Cellobiose'Doc_135496","h_idx":2,"t_idx":8,"r":"P17"},{"title":"b'Cellobiose'Doc_135536","h_idx":19,"t_idx":16,"r":"P17"},{"title":"b'Cellobiose'Doc_135536","h_idx":21,"t_idx":2,"r":"P17"},{"title":"b'Cellobiose'Doc_135542","h_idx":7,"t_idx":2,"r":"P17"},{"title":"b'Cellobiose'Doc_135544","h_idx":9,"t_idx":9,"r":"P17"},{"title":"b'beta-Alanine'Doc_135700","h_idx":5,"t_idx":2,"r":"P17"},{"title":"b'beta-Alanine'Doc_135704","h_idx":14,"t_idx":16,"r":"P17"},{"title":"b'beta-Alanine'Doc_135736","h_idx":17,"t_idx":9,"r":"P17"},{"title":"b'beta-Alanine'Doc_135737","h_idx":1,"t_idx":4,"r":"P17"},{"title":"b'beta-Alanine'Doc_135743","h_idx":23,"t_idx":5,"r":"P17"},{"title":"b'beta-Alanine'Doc_135743","h_idx":28,"t_idx":9,"r":"P17"},{"title":"b'3-aminopropanoic acid'Doc_135751","h_idx":12,"t_idx":5,"r":"P17"},{"title":"b'3-aminopropanoic acid'Doc_135751","h_idx":13,"t_idx":14,"r":"P17"},{"title":"b'3-aminopropanoic acid'Doc_135769","h_idx":9,"t_idx":5,"r":"P17"},{"title":"b'Cyclic AMP'Doc_135853","h_idx":5,"t_idx":32,"r":"P17"},{"title":"b'Cyclic AMP'Doc_135853","h_idx":6,"t_idx":2,"r":"P17"},{"title":"b'Cyclic AMP'Doc_135858","h_idx":5,"t_idx":32,"r":"P17"},{"title":"b'Cyclic AMP'Doc_135858","h_idx":6,"t_idx":28,"r":"P17"},{"title":"b'Cyclic AMP'Doc_135858","h_idx":6,"t_idx":30,"r":"P17"},{"title":"b'Cyclic AMP'Doc_135858","h_idx":6,"t_idx":32,"r":"P17"},{"title":"b'Cyclic AMP'Doc_135858","h_idx":7,"t_idx":24,"r":"P17"},{"title":"b'Cyclic AMP'Doc_135858","h_idx":7,"t_idx":26,"r":"P17"},{"title":"b'Cyclic AMP'Doc_135858","h_idx":7,"t_idx":27,"r":"P17"},{"title":"b'Cyclic AMP'Doc_135873","h_idx":17,"t_idx":34,"r":"P17"},{"title":"b'Cyclic AMP'Doc_135884","h_idx":3,"t_idx":12,"r":"P17"},{"title":"b'Cyclic AMP'Doc_135906","h_idx":38,"t_idx":38,"r":"P17"},{"title":"b'Cyclic AMP'Doc_135916","h_idx":11,"t_idx":26,"r":"P17"},{"title":"b'(4aR,6R,7R,7aS)-6-(6-amino-9H-purin-9-yl)-2,7-dihydroxy-hexahydro-2lambda5-furo[3,2-d][1,3,2]dioxaphosphinin-2-one'Doc_135948","h_idx":5,"t_idx":32,"r":"P17"},{"title":"b'(4aR,6R,7R,7aS)-6-(6-amino-9H-purin-9-yl)-2,7-dihydroxy-hexahydro-2lambda5-furo[3,2-d][1,3,2]dioxaphosphinin-2-one'Doc_135948","h_idx":6,"t_idx":2,"r":"P17"},{"title":"b'(4aR,6R,7R,7aS)-6-(6-amino-9H-purin-9-yl)-2,7-dihydroxy-hexahydro-2lambda5-furo[3,2-d][1,3,2]dioxaphosphinin-2-one'Doc_135953","h_idx":5,"t_idx":32,"r":"P17"},{"title":"b'(4aR,6R,7R,7aS)-6-(6-amino-9H-purin-9-yl)-2,7-dihydroxy-hexahydro-2lambda5-furo[3,2-d][1,3,2]dioxaphosphinin-2-one'Doc_135953","h_idx":6,"t_idx":28,"r":"P17"},{"title":"b'(4aR,6R,7R,7aS)-6-(6-amino-9H-purin-9-yl)-2,7-dihydroxy-hexahydro-2lambda5-furo[3,2-d][1,3,2]dioxaphosphinin-2-one'Doc_135953","h_idx":6,"t_idx":30,"r":"P17"},{"title":"b'(4aR,6R,7R,7aS)-6-(6-amino-9H-purin-9-yl)-2,7-dihydroxy-hexahydro-2lambda5-furo[3,2-d][1,3,2]dioxaphosphinin-2-one'Doc_135953","h_idx":6,"t_idx":32,"r":"P17"},{"title":"b'(4aR,6R,7R,7aS)-6-(6-amino-9H-purin-9-yl)-2,7-dihydroxy-hexahydro-2lambda5-furo[3,2-d][1,3,2]dioxaphosphinin-2-one'Doc_135953","h_idx":7,"t_idx":24,"r":"P17"},{"title":"b'(4aR,6R,7R,7aS)-6-(6-amino-9H-purin-9-yl)-2,7-dihydroxy-hexahydro-2lambda5-furo[3,2-d][1,3,2]dioxaphosphinin-2-one'Doc_135953","h_idx":7,"t_idx":26,"r":"P17"},{"title":"b'(4aR,6R,7R,7aS)-6-(6-amino-9H-purin-9-yl)-2,7-dihydroxy-hexahydro-2lambda5-furo[3,2-d][1,3,2]dioxaphosphinin-2-one'Doc_135953","h_idx":7,"t_idx":27,"r":"P17"},{"title":"b'(4aR,6R,7R,7aS)-6-(6-amino-9H-purin-9-yl)-2,7-dihydroxy-hexahydro-2lambda5-furo[3,2-d][1,3,2]dioxaphosphinin-2-one'Doc_135968","h_idx":17,"t_idx":34,"r":"P17"},{"title":"b'(4aR,6R,7R,7aS)-6-(6-amino-9H-purin-9-yl)-2,7-dihydroxy-hexahydro-2lambda5-furo[3,2-d][1,3,2]dioxaphosphinin-2-one'Doc_135979","h_idx":3,"t_idx":12,"r":"P17"},{"title":"b'(4aR,6R,7R,7aS)-6-(6-amino-9H-purin-9-yl)-2,7-dihydroxy-hexahydro-2lambda5-furo[3,2-d][1,3,2]dioxaphosphinin-2-one'Doc_136001","h_idx":38,"t_idx":38,"r":"P17"},{"title":"b'(4aR,6R,7R,7aS)-6-(6-amino-9H-purin-9-yl)-2,7-dihydroxy-hexahydro-2lambda5-furo[3,2-d][1,3,2]dioxaphosphinin-2-one'Doc_136010","h_idx":4,"t_idx":25,"r":"P17"},{"title":"b'(4aR,6R,7R,7aS)-6-(6-amino-9H-purin-9-yl)-2,7-dihydroxy-hexahydro-2lambda5-furo[3,2-d][1,3,2]dioxaphosphinin-2-one'Doc_136010","h_idx":5,"t_idx":19,"r":"P17"},{"title":"b'(4aR,6R,7R,7aS)-6-(6-amino-9H-purin-9-yl)-2,7-dihydroxy-hexahydro-2lambda5-furo[3,2-d][1,3,2]dioxaphosphinin-2-one'Doc_136016","h_idx":2,"t_idx":5,"r":"P17"},{"title":"b'(4aR,6R,7R,7aS)-6-(6-amino-9H-purin-9-yl)-2,7-dihydroxy-hexahydro-2lambda5-furo[3,2-d][1,3,2]dioxaphosphinin-2-one'Doc_136016","h_idx":11,"t_idx":9,"r":"P17"},{"title":"b'(4aR,6R,7R,7aS)-6-(6-amino-9H-purin-9-yl)-2,7-dihydroxy-hexahydro-2lambda5-furo[3,2-d][1,3,2]dioxaphosphinin-2-one'Doc_136025","h_idx":45,"t_idx":4,"r":"P17"},{"title":"b'(4aR,6R,7R,7aS)-6-(6-amino-9H-purin-9-yl)-2,7-dihydroxy-hexahydro-2lambda5-furo[3,2-d][1,3,2]dioxaphosphinin-2-one'Doc_136025","h_idx":46,"t_idx":7,"r":"P17"},{"title":"b'Acetoacetic acid'Doc_136064","h_idx":2,"t_idx":14,"r":"P17"},{"title":"b'Acetoacetic acid'Doc_136064","h_idx":5,"t_idx":17,"r":"P17"},{"title":"b'Acetoacetic acid'Doc_136066","h_idx":18,"t_idx":1,"r":"P17"},{"title":"b'Acetoacetic acid'Doc_136066","h_idx":26,"t_idx":14,"r":"P17"},{"title":"b'Acetoacetic acid'Doc_136109","h_idx":7,"t_idx":6,"r":"P17"},{"title":"b'Acetoacetic acid'Doc_136110","h_idx":0,"t_idx":24,"r":"P17"},{"title":"b'3-oxobutanoic acid'Doc_136160","h_idx":6,"t_idx":8,"r":"P17"},{"title":"b'3-oxobutanoic acid'Doc_136160","h_idx":8,"t_idx":8,"r":"P17"},{"title":"b'3-oxobutanoic acid'Doc_136163","h_idx":5,"t_idx":20,"r":"P17"},{"title":"b'3-oxobutanoic acid'Doc_136163","h_idx":14,"t_idx":15,"r":"P17"},{"title":"b'3-oxobutanoic acid'Doc_136201","h_idx":4,"t_idx":10,"r":"P17"},{"title":"b'3-oxobutanoic acid'Doc_136201","h_idx":7,"t_idx":10,"r":"P17"},{"title":"b\"Adenosine 3',5'-diphosphate\"Doc_136250","h_idx":6,"t_idx":8,"r":"P17"},{"title":"b\"Adenosine 3',5'-diphosphate\"Doc_136250","h_idx":8,"t_idx":8,"r":"P17"},{"title":"b\"Adenosine 3',5'-diphosphate\"Doc_136253","h_idx":5,"t_idx":20,"r":"P17"},{"title":"b\"Adenosine 3',5'-diphosphate\"Doc_136253","h_idx":14,"t_idx":15,"r":"P17"},{"title":"b\"Adenosine 3',5'-diphosphate\"Doc_136291","h_idx":4,"t_idx":10,"r":"P17"},{"title":"b\"Adenosine 3',5'-diphosphate\"Doc_136291","h_idx":7,"t_idx":10,"r":"P17"},{"title":"b'L-Carnitine'Doc_136399","h_idx":2,"t_idx":0,"r":"P17"},{"title":"b'L-Carnitine'Doc_136400","h_idx":16,"t_idx":17,"r":"P17"},{"title":"b'L-Carnitine'Doc_136400","h_idx":16,"t_idx":19,"r":"P17"},{"title":"b'L-Carnitine'Doc_136400","h_idx":18,"t_idx":2,"r":"P17"},{"title":"b'L-Carnitine'Doc_136400","h_idx":18,"t_idx":16,"r":"P17"},{"title":"b'L-Carnitine'Doc_136400","h_idx":18,"t_idx":17,"r":"P17"},{"title":"b'L-Carnitine'Doc_136414","h_idx":27,"t_idx":38,"r":"P17"},{"title":"b'L-Carnitine'Doc_136435","h_idx":8,"t_idx":38,"r":"P17"},{"title":"b'L-Carnitine'Doc_136435","h_idx":13,"t_idx":37,"r":"P17"},{"title":"b'L-Carnitine'Doc_136471","h_idx":25,"t_idx":19,"r":"P17"},{"title":"b'L-Carnitine'Doc_136472","h_idx":7,"t_idx":12,"r":"P17"},{"title":"b'L-Carnitine'Doc_136472","h_idx":7,"t_idx":14,"r":"P17"},{"title":"b'L-Carnitine'Doc_136472","h_idx":8,"t_idx":7,"r":"P17"},{"title":"b'L-Carnitine'Doc_136472","h_idx":8,"t_idx":21,"r":"P17"},{"title":"b'L-Carnitine'Doc_136472","h_idx":8,"t_idx":22,"r":"P17"},{"title":"b'L-Carnitine'Doc_136478","h_idx":44,"t_idx":27,"r":"P17"},{"title":"b'(3R)-3-hydroxy-4-(trimethylazaniumyl)butanoate'Doc_136504","h_idx":73,"t_idx":73,"r":"P17"},{"title":"b'(3R)-3-hydroxy-4-(trimethylazaniumyl)butanoate'Doc_136504","h_idx":76,"t_idx":34,"r":"P17"},{"title":"b'(3R)-3-hydroxy-4-(trimethylazaniumyl)butanoate'Doc_136543","h_idx":29,"t_idx":1,"r":"P17"},{"title":"b'(3R)-3-hydroxy-4-(trimethylazaniumyl)butanoate'Doc_136543","h_idx":37,"t_idx":26,"r":"P17"},{"title":"b'(3R)-3-hydroxy-4-(trimethylazaniumyl)butanoate'Doc_136543","h_idx":37,"t_idx":28,"r":"P17"},{"title":"b'(3R)-3-hydroxy-4-(trimethylazaniumyl)butanoate'Doc_136543","h_idx":38,"t_idx":6,"r":"P17"},{"title":"b'(3R)-3-hydroxy-4-(trimethylazaniumyl)butanoate'Doc_136543","h_idx":38,"t_idx":20,"r":"P17"},{"title":"b'(3R)-3-hydroxy-4-(trimethylazaniumyl)butanoate'Doc_136543","h_idx":38,"t_idx":21,"r":"P17"},{"title":"b'(3R)-3-hydroxy-4-(trimethylazaniumyl)butanoate'Doc_136551","h_idx":20,"t_idx":3,"r":"P17"},{"title":"b'Cortisol'Doc_136577","h_idx":3,"t_idx":9,"r":"P17"},{"title":"b'Cortisol'Doc_136577","h_idx":8,"t_idx":13,"r":"P17"},{"title":"b'Cortisol'Doc_136623","h_idx":5,"t_idx":39,"r":"P17"},{"title":"b'Cortisol'Doc_136623","h_idx":14,"t_idx":33,"r":"P17"},{"title":"b'Cortisol'Doc_136623","h_idx":14,"t_idx":35,"r":"P17"},{"title":"b'Cortisol'Doc_136623","h_idx":15,"t_idx":15,"r":"P17"},{"title":"b'Cortisol'Doc_136623","h_idx":15,"t_idx":29,"r":"P17"},{"title":"b'Cortisol'Doc_136623","h_idx":15,"t_idx":30,"r":"P17"},{"title":"b'Cortisol'Doc_136625","h_idx":77,"t_idx":48,"r":"P17"},{"title":"b'Cortisol'Doc_136648","h_idx":3,"t_idx":12,"r":"P17"},{"title":"b'Cortisol'Doc_136649","h_idx":0,"t_idx":8,"r":"P17"},{"title":"b'(1S,2R,10S,11S,14R,15S,17S)-14,17-dihydroxy-14-(2-hydroxyacetyl)-2,15-dimethyltetracyclo[8.7.0.0^{2,7}.0^{11,15}]heptadec-6-en-5-one'Doc_136690","h_idx":23,"t_idx":25,"r":"P17"},{"title":"b'(1S,2R,10S,11S,14R,15S,17S)-14,17-dihydroxy-14-(2-hydroxyacetyl)-2,15-dimethyltetracyclo[8.7.0.0^{2,7}.0^{11,15}]heptadec-6-en-5-one'Doc_136690","h_idx":24,"t_idx":21,"r":"P17"},{"title":"b'(1S,2R,10S,11S,14R,15S,17S)-14,17-dihydroxy-14-(2-hydroxyacetyl)-2,15-dimethyltetracyclo[8.7.0.0^{2,7}.0^{11,15}]heptadec-6-en-5-one'Doc_136690","h_idx":36,"t_idx":11,"r":"P17"},{"title":"b'(1S,2R,10S,11S,14R,15S,17S)-14,17-dihydroxy-14-(2-hydroxyacetyl)-2,15-dimethyltetracyclo[8.7.0.0^{2,7}.0^{11,15}]heptadec-6-en-5-one'Doc_136690","h_idx":37,"t_idx":31,"r":"P17"},{"title":"b'(1S,2R,10S,11S,14R,15S,17S)-14,17-dihydroxy-14-(2-hydroxyacetyl)-2,15-dimethyltetracyclo[8.7.0.0^{2,7}.0^{11,15}]heptadec-6-en-5-one'Doc_136693","h_idx":7,"t_idx":12,"r":"P17"},{"title":"b'(1S,2R,10S,11S,14R,15S,17S)-14,17-dihydroxy-14-(2-hydroxyacetyl)-2,15-dimethyltetracyclo[8.7.0.0^{2,7}.0^{11,15}]heptadec-6-en-5-one'Doc_136694","h_idx":3,"t_idx":19,"r":"P17"},{"title":"b'(1S,2R,10S,11S,14R,15S,17S)-14,17-dihydroxy-14-(2-hydroxyacetyl)-2,15-dimethyltetracyclo[8.7.0.0^{2,7}.0^{11,15}]heptadec-6-en-5-one'Doc_136709","h_idx":18,"t_idx":5,"r":"P17"},{"title":"b'(1S,2R,10S,11S,14R,15S,17S)-14,17-dihydroxy-14-(2-hydroxyacetyl)-2,15-dimethyltetracyclo[8.7.0.0^{2,7}.0^{11,15}]heptadec-6-en-5-one'Doc_136710","h_idx":11,"t_idx":6,"r":"P17"},{"title":"b'(1S,2R,10S,11S,14R,15S,17S)-14,17-dihydroxy-14-(2-hydroxyacetyl)-2,15-dimethyltetracyclo[8.7.0.0^{2,7}.0^{11,15}]heptadec-6-en-5-one'Doc_136715","h_idx":52,"t_idx":13,"r":"P17"},{"title":"b'(1S,2R,10S,11S,14R,15S,17S)-14,17-dihydroxy-14-(2-hydroxyacetyl)-2,15-dimethyltetracyclo[8.7.0.0^{2,7}.0^{11,15}]heptadec-6-en-5-one'Doc_136715","h_idx":52,"t_idx":73,"r":"P17"},{"title":"b'(1S,2R,10S,11S,14R,15S,17S)-14,17-dihydroxy-14-(2-hydroxyacetyl)-2,15-dimethyltetracyclo[8.7.0.0^{2,7}.0^{11,15}]heptadec-6-en-5-one'Doc_136720","h_idx":17,"t_idx":0,"r":"P17"},{"title":"b'(1S,2R,10S,11S,14R,15S,17S)-14,17-dihydroxy-14-(2-hydroxyacetyl)-2,15-dimethyltetracyclo[8.7.0.0^{2,7}.0^{11,15}]heptadec-6-en-5-one'Doc_136721","h_idx":15,"t_idx":9,"r":"P17"},{"title":"b'(1S,2R,10S,11S,14R,15S,17S)-14,17-dihydroxy-14-(2-hydroxyacetyl)-2,15-dimethyltetracyclo[8.7.0.0^{2,7}.0^{11,15}]heptadec-6-en-5-one'Doc_136721","h_idx":16,"t_idx":16,"r":"P17"},{"title":"b'(1S,2R,10S,11S,14R,15S,17S)-14,17-dihydroxy-14-(2-hydroxyacetyl)-2,15-dimethyltetracyclo[8.7.0.0^{2,7}.0^{11,15}]heptadec-6-en-5-one'Doc_136723","h_idx":30,"t_idx":20,"r":"P17"},{"title":"b'(1S,2R,10S,11S,14R,15S,17S)-14,17-dihydroxy-14-(2-hydroxyacetyl)-2,15-dimethyltetracyclo[8.7.0.0^{2,7}.0^{11,15}]heptadec-6-en-5-one'Doc_136723","h_idx":35,"t_idx":4,"r":"P17"},{"title":"b'(1S,2R,10S,11S,14R,15S,17S)-14,17-dihydroxy-14-(2-hydroxyacetyl)-2,15-dimethyltetracyclo[8.7.0.0^{2,7}.0^{11,15}]heptadec-6-en-5-one'Doc_136730","h_idx":22,"t_idx":0,"r":"P17"},{"title":"b'(1S,2R,10S,11S,14R,15S,17S)-14,17-dihydroxy-14-(2-hydroxyacetyl)-2,15-dimethyltetracyclo[8.7.0.0^{2,7}.0^{11,15}]heptadec-6-en-5-one'Doc_136730","h_idx":24,"t_idx":10,"r":"P17"},{"title":"b'(1S,2R,10S,11S,14R,15S,17S)-14,17-dihydroxy-14-(2-hydroxyacetyl)-2,15-dimethyltetracyclo[8.7.0.0^{2,7}.0^{11,15}]heptadec-6-en-5-one'Doc_136740","h_idx":22,"t_idx":2,"r":"P17"},{"title":"b'(1S,2R,10S,11S,14R,15S,17S)-14,17-dihydroxy-14-(2-hydroxyacetyl)-2,15-dimethyltetracyclo[8.7.0.0^{2,7}.0^{11,15}]heptadec-6-en-5-one'Doc_136741","h_idx":10,"t_idx":28,"r":"P17"},{"title":"b'(1S,2R,10S,11S,14R,15S,17S)-14,17-dihydroxy-14-(2-hydroxyacetyl)-2,15-dimethyltetracyclo[8.7.0.0^{2,7}.0^{11,15}]heptadec-6-en-5-one'Doc_136741","h_idx":12,"t_idx":2,"r":"P17"},{"title":"b'(1S,2R,10S,11S,14R,15S,17S)-14,17-dihydroxy-14-(2-hydroxyacetyl)-2,15-dimethyltetracyclo[8.7.0.0^{2,7}.0^{11,15}]heptadec-6-en-5-one'Doc_136743","h_idx":13,"t_idx":29,"r":"P17"},{"title":"b'(1S,2R,10S,11S,14R,15S,17S)-14,17-dihydroxy-14-(2-hydroxyacetyl)-2,15-dimethyltetracyclo[8.7.0.0^{2,7}.0^{11,15}]heptadec-6-en-5-one'Doc_136743","h_idx":21,"t_idx":10,"r":"P17"},{"title":"b'2-(N-methylcarbamimidamido)acetic acid'Doc_136754","h_idx":4,"t_idx":3,"r":"P17"},{"title":"b'2-(N-methylcarbamimidamido)acetic acid'Doc_136754","h_idx":5,"t_idx":6,"r":"P17"},{"title":"b'2-(N-methylcarbamimidamido)acetic acid'Doc_136756","h_idx":40,"t_idx":24,"r":"P17"},{"title":"b'Cholesterol'Doc_136757","h_idx":6,"t_idx":0,"r":"P17"},{"title":"b'Cholesterol'Doc_136757","h_idx":7,"t_idx":12,"r":"P17"},{"title":"b'(1S,2R,5S,10S,11S,14R,15R)-2,15-dimethyl-14-[(2R)-6-methylheptan-2-yl]tetracyclo[8.7.0.0^{2,7}.0^{11,15}]heptadec-7-en-5-ol'Doc_136763","h_idx":0,"t_idx":9,"r":"P17"},{"title":"b'(1S,2R,5S,10S,11S,14R,15R)-2,15-dimethyl-14-[(2R)-6-methylheptan-2-yl]tetracyclo[8.7.0.0^{2,7}.0^{11,15}]heptadec-7-en-5-ol'Doc_136763","h_idx":1,"t_idx":12,"r":"P17"},{"title":"b'4-[(1R)-1-hydroxy-2-(methylamino)ethyl]benzene-1,2-diol'Doc_136774","h_idx":19,"t_idx":17,"r":"P17"},{"title":"b'4-[(1R)-1-hydroxy-2-(methylamino)ethyl]benzene-1,2-diol'Doc_136775","h_idx":9,"t_idx":10,"r":"P17"},{"title":"b'Pipecolic acid'Doc_136786","h_idx":14,"t_idx":11,"r":"P17"},{"title":"b'Pipecolic acid'Doc_136787","h_idx":4,"t_idx":7,"r":"P17"},{"title":"b'Pipecolic acid'Doc_136812","h_idx":8,"t_idx":4,"r":"P17"},{"title":"b'Pipecolic acid'Doc_136812","h_idx":10,"t_idx":2,"r":"P17"},{"title":"b'Pipecolic acid'Doc_136856","h_idx":3,"t_idx":7,"r":"P17"},{"title":"b'Pipecolic acid'Doc_136860","h_idx":2,"t_idx":11,"r":"P17"},{"title":"b'piperidine-2-carboxylic acid'Doc_136881","h_idx":28,"t_idx":5,"r":"P17"},{"title":"b'piperidine-2-carboxylic acid'Doc_136881","h_idx":30,"t_idx":1,"r":"P17"},{"title":"b'piperidine-2-carboxylic acid'Doc_136906","h_idx":13,"t_idx":2,"r":"P17"},{"title":"b'piperidine-2-carboxylic acid'Doc_136926","h_idx":6,"t_idx":16,"r":"P17"},{"title":"b'piperidine-2-carboxylic acid'Doc_136951","h_idx":11,"t_idx":9,"r":"P17"},{"title":"b'Deoxyinosine'Doc_136977","h_idx":0,"t_idx":18,"r":"P17"},{"title":"b'Deoxyinosine'Doc_137000","h_idx":7,"t_idx":4,"r":"P17"},{"title":"b'Deoxyinosine'Doc_137020","h_idx":3,"t_idx":7,"r":"P17"},{"title":"b'9-[(2R,4S,5R)-4-hydroxy-5-(hydroxymethyl)oxolan-2-yl]-9H-purin-6-ol'Doc_137048","h_idx":12,"t_idx":1,"r":"P17"},{"title":"b'9-[(2R,4S,5R)-4-hydroxy-5-(hydroxymethyl)oxolan-2-yl]-9H-purin-6-ol'Doc_137102","h_idx":8,"t_idx":17,"r":"P17"},{"title":"b'(1Z)-prop-1-ene-1,2,3-tricarboxylic acid'Doc_137269","h_idx":10,"t_idx":16,"r":"P17"},{"title":"b'(1Z)-prop-1-ene-1,2,3-tricarboxylic acid'Doc_137273","h_idx":10,"t_idx":8,"r":"P17"},{"title":"b'(1Z)-prop-1-ene-1,2,3-tricarboxylic acid'Doc_137299","h_idx":16,"t_idx":14,"r":"P17"},{"title":"b'4-(2-aminoethyl)benzene-1,2-diol'Doc_137319","h_idx":12,"t_idx":15,"r":"P17"},{"title":"b'Dihydrothymine'Doc_137356","h_idx":21,"t_idx":1,"r":"P17"},{"title":"b'Dihydrothymine'Doc_137356","h_idx":32,"t_idx":12,"r":"P17"},{"title":"b'(5S)-5-methyl-1,3-diazinane-2,4-dione'Doc_137357","h_idx":52,"t_idx":38,"r":"P17"},{"title":"b'Cytidine triphosphate'Doc_137376","h_idx":3,"t_idx":24,"r":"P17"},{"title":"b'Cytidine triphosphate'Doc_137445","h_idx":21,"t_idx":14,"r":"P17"},{"title":"b'Cytidine triphosphate'Doc_137446","h_idx":11,"t_idx":2,"r":"P17"},{"title":"b'Cytidine triphosphate'Doc_137454","h_idx":23,"t_idx":8,"r":"P17"},{"title":"b'({[({[(2R,3S,4R,5R)-5-(4-amino-2-oxo-1,2-dihydropyrimidin-1-yl)-3,4-dihydroxyoxolan-2-yl]methoxy}(hydroxy)phosphoryl)oxy](hydroxy)phosphoryl}oxy)phosphonic acid'Doc_137473","h_idx":3,"t_idx":24,"r":"P17"},{"title":"b'({[({[(2R,3S,4R,5R)-5-(4-amino-2-oxo-1,2-dihydropyrimidin-1-yl)-3,4-dihydroxyoxolan-2-yl]methoxy}(hydroxy)phosphoryl)oxy](hydroxy)phosphoryl}oxy)phosphonic acid'Doc_137542","h_idx":21,"t_idx":14,"r":"P17"},{"title":"b'({[({[(2R,3S,4R,5R)-5-(4-amino-2-oxo-1,2-dihydropyrimidin-1-yl)-3,4-dihydroxyoxolan-2-yl]methoxy}(hydroxy)phosphoryl)oxy](hydroxy)phosphoryl}oxy)phosphonic acid'Doc_137543","h_idx":11,"t_idx":2,"r":"P17"},{"title":"b'({[({[(2R,3S,4R,5R)-5-(4-amino-2-oxo-1,2-dihydropyrimidin-1-yl)-3,4-dihydroxyoxolan-2-yl]methoxy}(hydroxy)phosphoryl)oxy](hydroxy)phosphoryl}oxy)phosphonic acid'Doc_137551","h_idx":23,"t_idx":8,"r":"P17"},{"title":"b'Deoxyguanosine'Doc_137570","h_idx":3,"t_idx":24,"r":"P17"},{"title":"b'Deoxyguanosine'Doc_137639","h_idx":21,"t_idx":14,"r":"P17"},{"title":"b'Deoxyguanosine'Doc_137640","h_idx":11,"t_idx":2,"r":"P17"},{"title":"b'Deoxyguanosine'Doc_137648","h_idx":23,"t_idx":8,"r":"P17"},{"title":"b'2-amino-9-[(2R,4S,5R)-4-hydroxy-5-(hydroxymethyl)oxolan-2-yl]-6,9-dihydro-1H-purin-6-one'Doc_137667","h_idx":3,"t_idx":24,"r":"P17"},{"title":"b'2-amino-9-[(2R,4S,5R)-4-hydroxy-5-(hydroxymethyl)oxolan-2-yl]-6,9-dihydro-1H-purin-6-one'Doc_137736","h_idx":21,"t_idx":14,"r":"P17"},{"title":"b'2-amino-9-[(2R,4S,5R)-4-hydroxy-5-(hydroxymethyl)oxolan-2-yl]-6,9-dihydro-1H-purin-6-one'Doc_137737","h_idx":11,"t_idx":2,"r":"P17"},{"title":"b'2-amino-9-[(2R,4S,5R)-4-hydroxy-5-(hydroxymethyl)oxolan-2-yl]-6,9-dihydro-1H-purin-6-one'Doc_137745","h_idx":23,"t_idx":8,"r":"P17"},{"title":"b'Glycerophosphocholine'Doc_137789","h_idx":5,"t_idx":4,"r":"P17"},{"title":"b'Glycerophosphocholine'Doc_137806","h_idx":3,"t_idx":9,"r":"P17"},{"title":"b'Glycerophosphocholine'Doc_137806","h_idx":3,"t_idx":13,"r":"P17"},{"title":"b'Glycerophosphocholine'Doc_137806","h_idx":4,"t_idx":3,"r":"P17"},{"title":"b'Glycerophosphocholine'Doc_137806","h_idx":4,"t_idx":7,"r":"P17"},{"title":"b'Glycerophosphocholine'Doc_137806","h_idx":4,"t_idx":27,"r":"P17"},{"title":"b'Glycerophosphocholine'Doc_137806","h_idx":4,"t_idx":28,"r":"P17"},{"title":"b'Glycerophosphocholine'Doc_137806","h_idx":5,"t_idx":1,"r":"P17"},{"title":"b'Glycerophosphocholine'Doc_137806","h_idx":8,"t_idx":5,"r":"P17"},{"title":"b'Glycerophosphocholine'Doc_137806","h_idx":9,"t_idx":3,"r":"P17"},{"title":"b'(2-{[(2R)-2,3-dihydroxypropyl phosphono]oxy}ethyl)trimethylazanium'Doc_137890","h_idx":32,"t_idx":5,"r":"P17"},{"title":"b'(2-{[(2R)-2,3-dihydroxypropyl phosphono]oxy}ethyl)trimethylazanium'Doc_137938","h_idx":5,"t_idx":6,"r":"P17"},{"title":"b'(2-{[(2R)-2,3-dihydroxypropyl phosphono]oxy}ethyl)trimethylazanium'Doc_137938","h_idx":5,"t_idx":10,"r":"P17"},{"title":"b'(2-{[(2R)-2,3-dihydroxypropyl phosphono]oxy}ethyl)trimethylazanium'Doc_137938","h_idx":6,"t_idx":12,"r":"P17"},{"title":"b'(2-{[(2R)-2,3-dihydroxypropyl phosphono]oxy}ethyl)trimethylazanium'Doc_137938","h_idx":6,"t_idx":16,"r":"P17"},{"title":"b'(2-{[(2R)-2,3-dihydroxypropyl phosphono]oxy}ethyl)trimethylazanium'Doc_137938","h_idx":7,"t_idx":16,"r":"P17"},{"title":"b'(2-{[(2R)-2,3-dihydroxypropyl phosphono]oxy}ethyl)trimethylazanium'Doc_137938","h_idx":7,"t_idx":17,"r":"P17"},{"title":"b'(2-{[(2R)-2,3-dihydroxypropyl phosphono]oxy}ethyl)trimethylazanium'Doc_137938","h_idx":8,"t_idx":2,"r":"P17"},{"title":"b'(2-{[(2R)-2,3-dihydroxypropyl phosphono]oxy}ethyl)trimethylazanium'Doc_137938","h_idx":13,"t_idx":2,"r":"P17"},{"title":"b'(2-{[(2R)-2,3-dihydroxypropyl phosphono]oxy}ethyl)trimethylazanium'Doc_137938","h_idx":14,"t_idx":12,"r":"P17"},{"title":"b'Dimethylamine'Doc_138005","h_idx":0,"t_idx":15,"r":"P17"},{"title":"b'Dimethylamine'Doc_138010","h_idx":17,"t_idx":2,"r":"P17"},{"title":"b'Dimethylamine'Doc_138010","h_idx":17,"t_idx":11,"r":"P17"},{"title":"b'Dimethylamine'Doc_138017","h_idx":14,"t_idx":9,"r":"P17"},{"title":"b'Dimethylamine'Doc_138028","h_idx":28,"t_idx":26,"r":"P17"},{"title":"b'Dimethylamine'Doc_138029","h_idx":35,"t_idx":26,"r":"P17"},{"title":"b'Dimethylamine'Doc_138031","h_idx":4,"t_idx":1,"r":"P17"},{"title":"b'dimethylamine'Doc_138060","h_idx":7,"t_idx":23,"r":"P17"},{"title":"b'dimethylamine'Doc_138066","h_idx":18,"t_idx":17,"r":"P17"},{"title":"b'dimethylamine'Doc_138066","h_idx":18,"t_idx":26,"r":"P17"},{"title":"b'dimethylamine'Doc_138073","h_idx":2,"t_idx":2,"r":"P17"},{"title":"b'dimethylamine'Doc_138086","h_idx":15,"t_idx":18,"r":"P17"},{"title":"b'dimethylamine'Doc_138091","h_idx":0,"t_idx":24,"r":"P17"},{"title":"b'dimethylamine'Doc_138093","h_idx":0,"t_idx":11,"r":"P17"},{"title":"b'dimethylamine'Doc_138122","h_idx":15,"t_idx":4,"r":"P17"},{"title":"b'dimethylamine'Doc_138127","h_idx":26,"t_idx":14,"r":"P17"},{"title":"b'dimethylamine'Doc_138127","h_idx":26,"t_idx":23,"r":"P17"},{"title":"b'Cytidine'Doc_138131","h_idx":26,"t_idx":38,"r":"P17"},{"title":"b'Cytidine'Doc_138159","h_idx":9,"t_idx":0,"r":"P17"},{"title":"b'Cytidine'Doc_138166","h_idx":7,"t_idx":7,"r":"P17"},{"title":"b'Cytidine'Doc_138168","h_idx":9,"t_idx":1,"r":"P17"},{"title":"b'Cytidine'Doc_138205","h_idx":0,"t_idx":11,"r":"P17"},{"title":"b'Cytidine'Doc_138213","h_idx":15,"t_idx":5,"r":"P17"},{"title":"b'Cytidine'Doc_138213","h_idx":15,"t_idx":14,"r":"P17"},{"title":"b'4-amino-1-[(2R,3R,4S,5R)-3,4-dihydroxy-5-(hydroxymethyl)oxolan-2-yl]-1,2-dihydropyrimidin-2-one'Doc_138224","h_idx":26,"t_idx":38,"r":"P17"},{"title":"b'4-amino-1-[(2R,3R,4S,5R)-3,4-dihydroxy-5-(hydroxymethyl)oxolan-2-yl]-1,2-dihydropyrimidin-2-one'Doc_138252","h_idx":9,"t_idx":0,"r":"P17"},{"title":"b'4-amino-1-[(2R,3R,4S,5R)-3,4-dihydroxy-5-(hydroxymethyl)oxolan-2-yl]-1,2-dihydropyrimidin-2-one'Doc_138259","h_idx":7,"t_idx":7,"r":"P17"},{"title":"b'4-amino-1-[(2R,3R,4S,5R)-3,4-dihydroxy-5-(hydroxymethyl)oxolan-2-yl]-1,2-dihydropyrimidin-2-one'Doc_138261","h_idx":9,"t_idx":1,"r":"P17"},{"title":"b'4-amino-1-[(2R,3R,4S,5R)-3,4-dihydroxy-5-(hydroxymethyl)oxolan-2-yl]-1,2-dihydropyrimidin-2-one'Doc_138297","h_idx":5,"t_idx":20,"r":"P17"},{"title":"b'4-amino-1-[(2R,3R,4S,5R)-3,4-dihydroxy-5-(hydroxymethyl)oxolan-2-yl]-1,2-dihydropyrimidin-2-one'Doc_138297","h_idx":13,"t_idx":17,"r":"P17"},{"title":"b'4-amino-1-[(2R,3R,4S,5R)-3,4-dihydroxy-5-(hydroxymethyl)oxolan-2-yl]-1,2-dihydropyrimidin-2-one'Doc_138300","h_idx":20,"t_idx":22,"r":"P17"},{"title":"b'4-amino-1-[(2R,3R,4S,5R)-3,4-dihydroxy-5-(hydroxymethyl)oxolan-2-yl]-1,2-dihydropyrimidin-2-one'Doc_138300","h_idx":21,"t_idx":22,"r":"P17"},{"title":"b'4-amino-1-[(2R,3R,4S,5R)-3,4-dihydroxy-5-(hydroxymethyl)oxolan-2-yl]-1,2-dihydropyrimidin-2-one'Doc_138311","h_idx":11,"t_idx":4,"r":"P17"},{"title":"b'4-amino-1-[(2R,3R,4S,5R)-3,4-dihydroxy-5-(hydroxymethyl)oxolan-2-yl]-1,2-dihydropyrimidin-2-one'Doc_138312","h_idx":2,"t_idx":6,"r":"P17"},{"title":"b'Dimethylglycine'Doc_138356","h_idx":4,"t_idx":6,"r":"P17"},{"title":"b'Dimethylglycine'Doc_138360","h_idx":11,"t_idx":2,"r":"P17"},{"title":"b'Dimethylglycine'Doc_138367","h_idx":10,"t_idx":7,"r":"P17"},{"title":"b'Dimethylglycine'Doc_138367","h_idx":10,"t_idx":8,"r":"P17"},{"title":"b'Dimethylglycine'Doc_138367","h_idx":13,"t_idx":23,"r":"P17"},{"title":"b'Dimethylglycine'Doc_138367","h_idx":14,"t_idx":8,"r":"P17"},{"title":"b'Dimethylglycine'Doc_138367","h_idx":14,"t_idx":11,"r":"P17"},{"title":"b'Dimethylglycine'Doc_138367","h_idx":14,"t_idx":19,"r":"P17"},{"title":"b'Dimethylglycine'Doc_138374","h_idx":34,"t_idx":28,"r":"P17"},{"title":"b'Dimethylglycine'Doc_138386","h_idx":15,"t_idx":30,"r":"P17"},{"title":"b'Dimethylglycine'Doc_138390","h_idx":13,"t_idx":1,"r":"P17"},{"title":"b'Dimethylglycine'Doc_138393","h_idx":24,"t_idx":18,"r":"P17"},{"title":"b'Dimethylglycine'Doc_138393","h_idx":24,"t_idx":19,"r":"P17"},{"title":"b'Dimethylglycine'Doc_138393","h_idx":26,"t_idx":34,"r":"P17"},{"title":"b'Dimethylglycine'Doc_138393","h_idx":27,"t_idx":7,"r":"P17"},{"title":"b'Dimethylglycine'Doc_138393","h_idx":27,"t_idx":10,"r":"P17"},{"title":"b'Dimethylglycine'Doc_138393","h_idx":27,"t_idx":18,"r":"P17"},{"title":"b'Dimethylglycine'Doc_138405","h_idx":4,"t_idx":7,"r":"P17"},{"title":"b'2-(dimethylamino)acetic acid'Doc_138410","h_idx":32,"t_idx":23,"r":"P17"},{"title":"b'2-(dimethylamino)acetic acid'Doc_138410","h_idx":47,"t_idx":8,"r":"P17"},{"title":"b'2-(dimethylamino)acetic acid'Doc_138410","h_idx":47,"t_idx":31,"r":"P17"},{"title":"b'2-(dimethylamino)acetic acid'Doc_138445","h_idx":23,"t_idx":6,"r":"P17"},{"title":"b'2-(dimethylamino)acetic acid'Doc_138449","h_idx":35,"t_idx":10,"r":"P17"},{"title":"b'2-(dimethylamino)acetic acid'Doc_138483","h_idx":20,"t_idx":21,"r":"P17"},{"title":"b'Citric acid'Doc_138518","h_idx":11,"t_idx":10,"r":"P17"},{"title":"b'Citric acid'Doc_138531","h_idx":10,"t_idx":1,"r":"P17"},{"title":"b'Citric acid'Doc_138548","h_idx":3,"t_idx":5,"r":"P17"},{"title":"b'Citric acid'Doc_138559","h_idx":0,"t_idx":13,"r":"P17"},{"title":"b'Citric acid'Doc_138559","h_idx":1,"t_idx":9,"r":"P17"},{"title":"b'2-hydroxypropane-1,2,3-tricarboxylic acid'Doc_138600","h_idx":2,"t_idx":20,"r":"P17"},{"title":"b'Cytidine monophosphate'Doc_138601","h_idx":25,"t_idx":31,"r":"P17"},{"title":"b'{[(2R,3S,4R,5R)-5-(4-amino-2-oxo-1,2-dihydropyrimidin-1-yl)-3,4-dihydroxyoxolan-2-yl]methoxy}phosphonic acid'Doc_138645","h_idx":18,"t_idx":22,"r":"P17"},{"title":"b'{[(2R,3S,4R,5R)-5-(4-amino-2-oxo-1,2-dihydropyrimidin-1-yl)-3,4-dihydroxyoxolan-2-yl]methoxy}phosphonic acid'Doc_138681","h_idx":15,"t_idx":8,"r":"P17"},{"title":"b'Choline'Doc_138687","h_idx":6,"t_idx":1,"r":"P17"},{"title":"b'Choline'Doc_138689","h_idx":6,"t_idx":14,"r":"P17"},{"title":"b'Choline'Doc_138722","h_idx":16,"t_idx":9,"r":"P17"},{"title":"b'Choline'Doc_138726","h_idx":0,"t_idx":1,"r":"P17"},{"title":"b'Choline'Doc_138768","h_idx":6,"t_idx":1,"r":"P17"},{"title":"b'Choline'Doc_138769","h_idx":28,"t_idx":4,"r":"P17"},{"title":"b'Choline'Doc_138769","h_idx":29,"t_idx":15,"r":"P17"},{"title":"b'Choline'Doc_138769","h_idx":30,"t_idx":7,"r":"P17"},{"title":"b'Choline'Doc_138776","h_idx":20,"t_idx":8,"r":"P17"},{"title":"b'(2-hydroxyethyl)trimethylazanium'Doc_138790","h_idx":16,"t_idx":17,"r":"P17"},{"title":"b'(2-hydroxyethyl)trimethylazanium'Doc_138832","h_idx":1,"t_idx":6,"r":"P17"},{"title":"b'(2-hydroxyethyl)trimethylazanium'Doc_138835","h_idx":4,"t_idx":8,"r":"P17"},{"title":"b'D-Xylose'Doc_138873","h_idx":6,"t_idx":2,"r":"P17"},{"title":"b'D-Xylose'Doc_138876","h_idx":7,"t_idx":4,"r":"P17"},{"title":"b'D-Xylose'Doc_138876","h_idx":8,"t_idx":14,"r":"P17"},{"title":"b'D-Xylose'Doc_138876","h_idx":9,"t_idx":5,"r":"P17"},{"title":"b'D-Xylose'Doc_138882","h_idx":11,"t_idx":13,"r":"P17"},{"title":"b'D-Xylose'Doc_138900","h_idx":4,"t_idx":11,"r":"P17"},{"title":"b'D-Xylose'Doc_138920","h_idx":6,"t_idx":4,"r":"P17"},{"title":"b'D-Xylose'Doc_138920","h_idx":26,"t_idx":4,"r":"P17"},{"title":"b'(3R,4S,5R)-oxane-2,3,4,5-tetrol'Doc_138955","h_idx":6,"t_idx":2,"r":"P17"},{"title":"b'(3R,4S,5R)-oxane-2,3,4,5-tetrol'Doc_138958","h_idx":7,"t_idx":4,"r":"P17"},{"title":"b'(3R,4S,5R)-oxane-2,3,4,5-tetrol'Doc_138958","h_idx":8,"t_idx":14,"r":"P17"},{"title":"b'(3R,4S,5R)-oxane-2,3,4,5-tetrol'Doc_138958","h_idx":9,"t_idx":5,"r":"P17"},{"title":"b'(3R,4S,5R)-oxane-2,3,4,5-tetrol'Doc_138964","h_idx":11,"t_idx":13,"r":"P17"},{"title":"b'(3R,4S,5R)-oxane-2,3,4,5-tetrol'Doc_138982","h_idx":4,"t_idx":11,"r":"P17"},{"title":"b'(3R,4S,5R)-oxane-2,3,4,5-tetrol'Doc_139002","h_idx":6,"t_idx":4,"r":"P17"},{"title":"b'(3R,4S,5R)-oxane-2,3,4,5-tetrol'Doc_139002","h_idx":26,"t_idx":4,"r":"P17"},{"title":"b'L-Cystathionine'Doc_139037","h_idx":6,"t_idx":2,"r":"P17"},{"title":"b'L-Cystathionine'Doc_139040","h_idx":7,"t_idx":4,"r":"P17"},{"title":"b'L-Cystathionine'Doc_139040","h_idx":8,"t_idx":14,"r":"P17"},{"title":"b'L-Cystathionine'Doc_139040","h_idx":9,"t_idx":5,"r":"P17"},{"title":"b'L-Cystathionine'Doc_139046","h_idx":11,"t_idx":13,"r":"P17"},{"title":"b'L-Cystathionine'Doc_139064","h_idx":4,"t_idx":11,"r":"P17"},{"title":"b'L-Cystathionine'Doc_139084","h_idx":6,"t_idx":4,"r":"P17"},{"title":"b'L-Cystathionine'Doc_139084","h_idx":26,"t_idx":4,"r":"P17"},{"title":"b'(2S)-2-amino-4-{[(2R)-2-amino-2-carboxyethyl]sulfanyl}butanoic acid'Doc_139119","h_idx":6,"t_idx":2,"r":"P17"},{"title":"b'(2S)-2-amino-4-{[(2R)-2-amino-2-carboxyethyl]sulfanyl}butanoic acid'Doc_139122","h_idx":7,"t_idx":4,"r":"P17"},{"title":"b'(2S)-2-amino-4-{[(2R)-2-amino-2-carboxyethyl]sulfanyl}butanoic acid'Doc_139122","h_idx":8,"t_idx":14,"r":"P17"},{"title":"b'(2S)-2-amino-4-{[(2R)-2-amino-2-carboxyethyl]sulfanyl}butanoic acid'Doc_139122","h_idx":9,"t_idx":5,"r":"P17"},{"title":"b'(2S)-2-amino-4-{[(2R)-2-amino-2-carboxyethyl]sulfanyl}butanoic acid'Doc_139128","h_idx":11,"t_idx":13,"r":"P17"},{"title":"b'(2S)-2-amino-4-{[(2R)-2-amino-2-carboxyethyl]sulfanyl}butanoic acid'Doc_139146","h_idx":4,"t_idx":11,"r":"P17"},{"title":"b'(2S)-2-amino-4-{[(2R)-2-amino-2-carboxyethyl]sulfanyl}butanoic acid'Doc_139166","h_idx":6,"t_idx":4,"r":"P17"},{"title":"b'(2S)-2-amino-4-{[(2R)-2-amino-2-carboxyethyl]sulfanyl}butanoic acid'Doc_139166","h_idx":26,"t_idx":4,"r":"P17"},{"title":"b'Deoxyadenosine'Doc_139201","h_idx":6,"t_idx":2,"r":"P17"},{"title":"b'Deoxyadenosine'Doc_139204","h_idx":7,"t_idx":4,"r":"P17"},{"title":"b'Deoxyadenosine'Doc_139204","h_idx":8,"t_idx":14,"r":"P17"},{"title":"b'Deoxyadenosine'Doc_139204","h_idx":9,"t_idx":5,"r":"P17"},{"title":"b'Deoxyadenosine'Doc_139210","h_idx":11,"t_idx":13,"r":"P17"},{"title":"b'Deoxyadenosine'Doc_139228","h_idx":4,"t_idx":11,"r":"P17"},{"title":"b'Deoxyadenosine'Doc_139248","h_idx":6,"t_idx":4,"r":"P17"},{"title":"b'Deoxyadenosine'Doc_139248","h_idx":26,"t_idx":4,"r":"P17"},{"title":"b'(2R,3S,5R)-5-(6-amino-9H-purin-9-yl)-2-(hydroxymethyl)oxolan-3-ol'Doc_139283","h_idx":6,"t_idx":2,"r":"P17"},{"title":"b'(2R,3S,5R)-5-(6-amino-9H-purin-9-yl)-2-(hydroxymethyl)oxolan-3-ol'Doc_139286","h_idx":7,"t_idx":4,"r":"P17"},{"title":"b'(2R,3S,5R)-5-(6-amino-9H-purin-9-yl)-2-(hydroxymethyl)oxolan-3-ol'Doc_139286","h_idx":8,"t_idx":14,"r":"P17"},{"title":"b'(2R,3S,5R)-5-(6-amino-9H-purin-9-yl)-2-(hydroxymethyl)oxolan-3-ol'Doc_139286","h_idx":9,"t_idx":5,"r":"P17"},{"title":"b'(2R,3S,5R)-5-(6-amino-9H-purin-9-yl)-2-(hydroxymethyl)oxolan-3-ol'Doc_139292","h_idx":11,"t_idx":13,"r":"P17"},{"title":"b'(2R,3S,5R)-5-(6-amino-9H-purin-9-yl)-2-(hydroxymethyl)oxolan-3-ol'Doc_139310","h_idx":4,"t_idx":11,"r":"P17"},{"title":"b'(2R,3S,5R)-5-(6-amino-9H-purin-9-yl)-2-(hydroxymethyl)oxolan-3-ol'Doc_139330","h_idx":6,"t_idx":4,"r":"P17"},{"title":"b'(2R,3S,5R)-5-(6-amino-9H-purin-9-yl)-2-(hydroxymethyl)oxolan-3-ol'Doc_139330","h_idx":26,"t_idx":4,"r":"P17"},{"title":"b'Galactitol'Doc_139365","h_idx":6,"t_idx":2,"r":"P17"},{"title":"b'Galactitol'Doc_139368","h_idx":7,"t_idx":4,"r":"P17"},{"title":"b'Galactitol'Doc_139368","h_idx":8,"t_idx":14,"r":"P17"},{"title":"b'Galactitol'Doc_139368","h_idx":9,"t_idx":5,"r":"P17"},{"title":"b'Galactitol'Doc_139374","h_idx":11,"t_idx":13,"r":"P17"},{"title":"b'Galactitol'Doc_139390","h_idx":8,"t_idx":8,"r":"P17"},{"title":"b'Galactitol'Doc_139390","h_idx":11,"t_idx":11,"r":"P17"},{"title":"b'Galactitol'Doc_139392","h_idx":36,"t_idx":51,"r":"P17"},{"title":"b'Galactitol'Doc_139392","h_idx":38,"t_idx":7,"r":"P17"}]